Workbook

Sheet Read me
A1: STEM PhD Atlas: owner dashboard
A2: Weekly (20 min): copy last week's numbers from Gumroad into 'Weekly actuals' (yellow cells only).
A3: 'Gates' turns green or red automatically against the Dec 15 decision rules.
A4: 'Forecast' is the scenario model from research/financials.py ($5 list; about $2 in India via Gumroad PPP). It is NOT actual data.
A5: Free copies sent with STUDENTAID or CLUBCOPY count as neither paid orders nor revenue.
A6: 'Hours' is your study-permit self-employment log. Count every business hour.
A7: Never type estimates into 'Weekly actuals'. Leave a cell blank if you don't know.

Sheet Weekly actuals
A1: Week starting | B1: Product views | C1: Sample downloads | D1: Paid orders | E1: Orders from unrelated buyers | F1: Refunds | G1: Gross revenue USD | H1: Gumroad payout USD | I1: Network orders (UTM whatsapp + group + alumni + club) | J1: Reddit orders (UTM reddit_profile) | K1: Usefulness replies | L1: Concrete benefits reported | M1: Data errors reported | N1: Orders from India | O1: Batch licences sold | P1: Free copies sent (STUDENTAID + CLUBCOPY) | Q1: Notes
A2: 46321
A3: 46328
A4: 46335
A5: 46342
A6: 46349
A7: 46356
A8: 46363
A9: 46370
A10: 46377
A11: 46384
A12: 46391
A13: 46398
A14: Total | B14: =SUM(B2:B13) | C14: =SUM(C2:C13) | D14: =SUM(D2:D13) | E14: =SUM(E2:E13) | F14: =SUM(F2:F13) | G14: =SUM(G2:G13) | H14: =SUM(H2:H13) | I14: =SUM(I2:I13) | ... P14: =SUM(P2:P13)

Sheet Gates
A1: Dec 15 gate | B1: Target | C1: Actual | D1: Status
A2: Paid orders | B2: >=10 | C2: ='Weekly actuals'!D14 | D2: =IF(C2>=10,"PASS","not yet")
A3: Retained orders from unrelated buyers | B3: >=2 | C3: ='Weekly actuals'!E14 | D3: =IF(C3>=2,"PASS","not yet")
A4: Refund rate (refunds / paid orders) | B4: <=10% | C4: =IF('Weekly actuals'!D14=0,0,'Weekly actuals'!F14/'Weekly actuals'!D14) | D4: =IF(AND('Weekly actuals'!D14>0,C4<=0.1),"PASS",IF('Weekly actuals'!D14=0,"no orders","FAIL"))
A5: Buyers reporting a concrete benefit | B5: >=2 | C5: ='Weekly actuals'!L14 | D5: =IF(C5>=2,"PASS","not yet")
A6: Critical data errors reported | B6: 0 | C6: ='Weekly actuals'!M14 | D6: =IF(C6=0,"PASS","FIX")
A7: Sample downloads (for the 'change' rule) | B7: >=50 | C7: ='Weekly actuals'!C14 | D7: =IF(C7>=50,"reached","below")
A9: Decision (Dec 15) | D9: =IF(COUNTIF(D2:D6,"PASS")=5,"PROCEED",IF(OR(C7>=50,C2>=5),"CHANGE offer/price/channel, one more cycle",IF(AND(C7<20,C3=0),"STOP (keep listing passive)","CHANGE")))

Sheet Forecast
A1: Scenario | B1: Period | C1: Orders | D1: Avg price | E1: Gross | F1: Fees | G1: Refunds | H1: Payout fee | I1: Net | J1: Owner hours | K1: Net per hour
A2: Conservative | B2: This season (Nov 2026-Jan 2027) | C2: 10 | D2: 2.6 | E2: 26 | F2: 10.75 | G2: 2.08 | H2: 0.26 | I2: 12.91 | J2: 12 | K2: 1.08
A3: Conservative | B3: Next full season (Aug 2027-Jan 2028) | C3: 50 | D3: 2.6 | E3: 130 | F3: 53.73 | G3: 10.4 | H3: 1.32 | I3: 64.55 | J3: 30 | K3: 2.15
A4: Base | B4: This season (Nov 2026-Jan 2027) | C4: 40 | D4: 2.75 | E4: 110 | F4: 44.06 | G4: 5.5 | H4: 1.21 | I4: 59.23 | J4: 14 | K4: 4.23
A5: Base | B5: Next full season (Aug 2027-Jan 2028) | C5: 200 | D5: 2.75 | E5: 550 | F5: 220.29 | G5: 27.5 | H5: 6.04 | I5: 296.17 | J5: 34 | K5: 8.71
A6: Optimistic | B6: This season (Nov 2026-Jan 2027) | C6: 120 | D6: 2.9 | E6: 348 | F6: 133.83 | G6: 13.92 | H6: 4.01 | I6: 196.25 | J6: 18 | K6: 10.9
A7: Optimistic | B7: Next full season (Aug 2027-Jan 2028) | C7: 600 | D7: 2.9 | E7: 1740 | F7: 669.15 | G7: 69.6 | H7: 20.03 | I7: 981.23 | J7: 45 | K7: 21.81
A9: These are assumptions (see research/financials.py), not results.

Sheet Expenses
A1: Date | B1: Item | C1: Amount | D1: Currency | E1: Approved by owner? | F1: Notes
B2: Gumroad account | C2: 0 | D2: USD | E2: n/a | F2: No monthly fee; per-sale fees only
B3: GitHub Actions source watch | C3: 0 | D3: USD | E3: n/a | F3: Within free minutes
B21: Total (cap this cycle: USD 30) | C21: =SUM(C2:C20)

Sheet Hours
A1: Date | B1: Task | C1: Minutes | D1: Week starting (auto) | E1: Notes | G1: Week starting | H1: Business hours | J1: Reminder: self-employment counts toward the 24 h/week off-campus limit during regular terms (IRCC). Add any other off-campus work (e.g., SpecReply) here too.
D2: =IF(A2="","",A2-WEEKDAY(A2,3)) | G2: 46321 | H2: =SUMIF($D$2:$D$201,G2,$C$2:$C$201)/60
D3: =IF(A3="","",A3-WEEKDAY(A3,3)) | G3: 46328 | H3: =SUMIF($D$2:$D$201,G3,$C$2:$C$201)/60
D4: =IF(A4="","",A4-WEEKDAY(A4,3)) | G4: 46335 | H4: =SUMIF($D$2:$D$201,G4,$C$2:$C$201)/60
D5: =IF(A5="","",A5-WEEKDAY(A5,3)) | G5: 46342 | H5: =SUMIF($D$2:$D$201,G5,$C$2:$C$201)/60
D6: =IF(A6="","",A6-WEEKDAY(A6,3)) | G6: 46349 | H6: =SUMIF($D$2:$D$201,G6,$C$2:$C$201)/60
D7: =IF(A7="","",A7-WEEKDAY(A7,3)) | G7: 46356 | H7: =SUMIF($D$2:$D$201,G7,$C$2:$C$201)/60
D8: =IF(A8="","",A8-WEEKDAY(A8,3)) | G8: 46363 | H8: =SUMIF($D$2:$D$201,G8,$C$2:$C$201)/60
D9: =IF(A9="","",A9-WEEKDAY(A9,3)) | G9: 46370 | H9: =SUMIF($D$2:$D$201,G9,$C$2:$C$201)/60
D10: =IF(A10="","",A10-WEEKDAY(A10,3)) | G10: 46377 | H10: =SUMIF($D$2:$D$201,G10,$C$2:$C$201)/60
D11: =IF(A11="","",A11-WEEKDAY(A11,3)) | G11: 46384 | H11: =SUMIF($D$2:$D$201,G11,$C$2:$C$201)/60
D12: =IF(A12="","",A12-WEEKDAY(A12,3)) | G12: 46391 | H12: =SUMIF($D$2:$D$201,G12,$C$2:$C$201)/60
D13: =IF(A13="","",A13-WEEKDAY(A13,3)) | G13: 46398 | H13: =SUMIF($D$2:$D$201,G13,$C$2:$C$201)/60
D14: =IF(A14="","",A14-WEEKDAY(A14,3))
D15: =IF(A15="","",A15-WEEKDAY(A15,3))
D16: =IF(A16="","",A16-WEEKDAY(A16,3))
D17: =IF(A17="","",A17-WEEKDAY(A17,3))
D18: =IF(A18="","",A18-WEEKDAY(A18,3))
D19: =IF(A19="","",A19-WEEKDAY(A19,3))
D20: =IF(A20="","",A20-WEEKDAY(A20,3))
D21: =IF(A21="","",A21-WEEKDAY(A21,3))
D22: =IF(A22="","",A22-WEEKDAY(A22,3))
D23: =IF(A23="","",A23-WEEKDAY(A23,3))
D24: =IF(A24="","",A24-WEEKDAY(A24,3))
D25: =IF(A25="","",A25-WEEKDAY(A25,3))
... D201: =IF(A201="","",A201-WEEKDAY(A201,3))
