Workbook

Sheet Start
A1: Physics PhD Atlas 2027: planner workbook
A2: Version 1.1 · 82 programs · data checked October 22, 2026
A4: 1. Programs: every program with deadline, fee, waivers, tests, supervisor rule and funding. Filter with the header arrows.
A5: 2. Shortlist: choose a program from the drop-down in column A; the other columns fill in automatically. Yellow cells are yours to edit.
A6: 3. Budget: totals your shortlisted application fees by currency. Add score-sending and transcript costs from the official sites, and today's exchange rates.
A7: 4. Recommenders and Supervisor outreach: track requests; follow-up dates calculate themselves.
A8: 5. Sources: the exact official sentence and link behind every value.
A10: 'Not stated' = the official pages checked did not say (not a 'no'). Always confirm on the official page before paying or submitting.
A11: Not affiliated with any university. Not immigration, visa or legal advice.

Sheet Programs
A1: Program | B1: Institution and department | C1: Country | D1: Region | E1: Deadline | F1: Deadline note | G1: Fee amount | H1: Fee currency | I1: Intl fee waiver | J1: Fee waiver detail | K1: GRE General | L1: Physics GRE | M1: TOEFL minimum | N1: English waiver | O1: English detail | P1: Supervisor | Q1: Supervisor detail | R1: Funding | S1: Funding detail | T1: Entry route | U1: Notes | V1: Admissions page | W1: Checked
A2: Aalto | B2: Aalto University · Doctoral Programme in Science (SCI), School of Science (incl. Applied Physics) | C2: Finland | D2: Uusimaa (Espoo) | E2: Rolling | F2: Continuous admission with roughly monthly cut-offs (nothing is processed in July); the last 2026 cut-offs are 3 Nov and 1 Dec 2026. Salaried doctoral researcher positions are advertised and applied for separately | G2: Not stated | I2: Not stated | J2: Not stated on the page checked | K2: Not stated | L2: Not stated | M2: 92 | N2: Yes | O2: India is on Aalto's list: an English-medium degree (at least a 3-year bachelor's or a 1-year master's), at least half completed in English while living in India, counts if the language is stated on the certificate or transcript | P2: Required | Q2: You must have a supervising professor in your intended research field before you submit the application | R2: Competitive | S2: Not automatic: fund the PhD through a salaried doctoral researcher position (advertised separately) or grants. A full-time study right needs funding secured for at least 6 months; unfunded part-time study is possible in some cases. No tuition fees | T2: Master's usually required | U2: Physics is one of the fields of the Aalto Doctoral Programme in Science (School of Science, e.g. Department of Applied Physics). There are two routes: get a salaried doctoral researcher position first and then apply for the study right, or apply for the study right with other funding. The language rules are labelled for 2026 admissions, and the TOEFL minimum is given only on the old 0-120 scale. Cut-off dates for 2027 were not yet published. | V2: https://www.aalto.fi/en/study-options/aalto-doctoral-programme-in-science-0 | W2: 2026-10-21
A3: Boston University | B3: Boston University · Department of Physics | C3: USA | D3: Massachusetts | E3: 46371 | F3: December 15, 23:59 ET; all documents must be posted. Year inferred. | G3: 95 | H3: USD | I3: Domestic only | J3: Central office waivers are domestic-only; international applicants may ask the program directly | K3: Optional | L3: Recommended | M3: Not stated | N3: Not stated | O3: Not stated on the page checked | P3: Not stated | Q3: No pre-application supervisor requirement mentioned | R3: Typical | S3: RAs and TAs receive tuition, fees and basic medical insurance plus a stipend | T3: Not stated | U3: BU explicitly refuses hardship-based fee waivers for international applicants at the central level. | V3: https://www.bu.edu/physics/graduate-program/graduate-program-admissions/ | W3: 2026-10-21
A4: Caltech | B4: California Institute of Technology · Department of Physics (PMA) | C4: USA | D4: California | E4: 46371 | F4: December 15 (catalog). Year inferred for Fall 2027. | G4: Not stated | I4: Limited | J4: Waivers are requested inside the online application; eligibility rules are not stated on the department page | K4: Recommended | L4: Required | M4: Not stated | N4: Not stated | O4: Not stated on the page checked | P4: Not stated | Q4: No pre-application supervisor requirement mentioned | R4: Not stated | S4: Not stated on the page checked | T4: Not stated | U4: Astronomy faculty can supervise physics students and vice versa. | V4: https://physics.caltech.edu/academics/graduate-studies/information-for-applicants | W4: 2026-10-21
A5: Carleton University | B5: Carleton University · Department of Physics | C5: Canada | D5: Ontario | E5: 46402 | F5: January 15 (Fall entry); late applications considered if openings remain. Year inferred for Fall 2027. | G5: 125 | H5: CAD | I5: None | J5: Graduate application fees are not waived | K5: Not stated | L5: Not stated | M5: 86 | N5: No | O5: Exemption only for English-taught degrees from countries whose primary language is English (India does not qualify) or a recent Canadian degree; medium-of-instruction letters are explicitly not accepted | P5: Not stated | Q5: Not stated on the page checked | R5: Competitive | S5: University-level statement: applicants are automatically considered for admission funding (TA, research stipend, scholarships) and notified in the offer if eligible; no guaranteed minimum stated on the pages checked | T5: Master's usually required | U5: PhD streams: Particle Physics and Medical Physics (CAMPEP-accredited), run jointly with uOttawa through the Ottawa-Carleton Institute for Physics. The department site (physics.carleton.ca) returned errors on every fetch, so supervisor and GRE policy could not be checked. | V5: https://graduate.carleton.ca/program/physics-doctoral-programs/ | W5: 2026-10-21
A6: Chalmers | B6: Chalmers University of Technology · Graduate School in Physics, Department of Physics and Astronomy | C6: Sweden | D6: Västra Götaland (Gothenburg) | E6: Per position | F6: No central deadline: doctoral positions are advertised under Vacant positions throughout the year, each with its own deadline | G6: 0 | I6: No fee | J6: No fee to waive | K6: Not stated | L6: Not stated | M6: 90 | N6: Conditional | O6: Indian upper-secondary English can meet the requirement: CBSE (2008 onwards) or CISCE Class XII English grades, or an English-medium upper secondary certificate. The India page offers no degree-based route, so otherwise take a test | P6: Not stated | Q6: Not stated on the page checked | R6: Guaranteed | S6: Doctoral students are employed by Chalmers on a monthly salary (fixed-term, generally at most five years), with up to 20% teaching or departmental work | T6: Master's usually required | U6: The Graduate School in Physics is run by the Department of Physics and Astronomy. Its syllabus sections (including entry requirements) are collapsed on the page and did not appear in the text checked, so the rules above are Chalmers-wide. Licentiate after about two years; doctorate after four to five years. | V6: https://www.chalmers.se/en/research/doctoral-studies/graduate-schools/physics/ | W6: 2026-10-21
A7: Columbia | B7: Columbia University · Department of Physics | C7: USA | D7: New York | E7: 46359 | F7: December 3, 2026 for Fall 2027 (early!) | G7: 120 | H7: USD | I7: Available | J7: GSAS considers waivers for financial need, personal hardship or other onerous circumstances | K7: Optional | L7: Optional | M7: Not stated | N7: Conditional | O7: Rule is based on the official language of your degree institution's country; English is an official language in India, so ask GSAS how this applies to you | P7: Not stated | Q7: No pre-application supervisor requirement mentioned | R7: Guaranteed | S7: Prevailing stipend plus tuition and fees for six years in good standing | T7: Not stated | U7: Three letters; personal statement. One of the earliest deadlines in this list. | V7: https://www.physics.columbia.edu/content/applying-columbia-physics-graduate-program | W7: 2026-10-21
A8: Cornell | B8: Cornell University · Department of Physics | C8: USA | D8: New York | E8: 46371 | F8: December 15: all materials incl. test scores must be received. Year inferred. | G8: 105 | H8: USD | I8: Available | J8: Can be requested for financial hardship or extenuating circumstances (Graduate School criteria) | K8: Not stated | L8: Required | M8: Sections | N8: Not stated | O8: Standing exemptions on the Graduate School site (not checked) | P8: Not stated | Q8: No pre-application supervisor requirement mentioned | R8: Guaranteed | S8: 6 years of full support in good standing (fellowships, TA, RA) | T8: Direct from bachelor's | U8: Applied Physics (AEP) is a separate Cornell field with different GRE rules. | V8: https://physics.cornell.edu/prospective-graduate-students | W8: 2026-10-21
A9: Dalhousie University | B9: Dalhousie University · Department of Physics and Atmospheric Science | C9: Canada | D9: Nova Scotia | E9: 46478 | F9: Formal application: April 1 for non-Canadian applicants for September admission (FGS general deadline; Canadians June 1). Free department pre-application first, reviewed September 1 to April 30, so start well before. Year inferred for September 2027. | G9: 115 | H9: CAD | I9: Not stated | J9: Not stated on the page checked | K9: Not required | L9: Not required | M9: 92 | N9: Conditional | O9: Waiver can be requested (not automatic) if your degree is from a recognized university with English as the language of instruction in a country where English is an official language; English is an official language of India, but confirm the waiver with the program | P9: Required | Q9: Admission depends on finding a supervisor through the free pre-application/interview; the formal application is submitted only with a supervisor's support and names the supervisor | R9: Guaranteed | S9: Every full-time MSc/PhD student funded; for students of primary-appointment faculty, guaranteed at least CAD 2,000/month take-home on average (CAD 24,000/yr after tuition) and CAD 33,000/yr total; PhD support normally 4 years; internationals funded on the same terms | T9: Either | U9: Apply via a free department pre-application first; a professor interviews you and funding is fixed before the formal FGS application. International PhD tuition equals domestic. Department Graduate Scholarship (CAD 20,000/yr, GPA 3.7+) open to internationals. | V9: https://www.dal.ca/faculty/science/physics/graduate/apply.html | W9: 2026-10-21
A10: TU Delft | B10: Delft University of Technology · Faculty of Applied Sciences (TNW), applied physics departments | C10: Netherlands | D10: South Holland (Delft) | E10: Per position | F10: No central deadline: apply to a specific advertised PhD position (each vacancy has its own deadline) | G10: Not stated | I10: Not stated | J10: Not stated on the pages checked | K10: Not stated | L10: Not stated | M10: 100 | N10: Yes | O10: In principle exempt with an English-taught master's degree; if your English is judged insufficient during selection you may be asked to take a placement test at TU Delft | P10: Required | Q10: You apply to a specific position and are employed in your supervisor's department; the application process includes a conversation with the professor | R10: Typical | S10: Regular PhD positions are four-year employment contracts with a salary under the Dutch universities' collective labour agreement; if no position is available you must find your own scholarship or grant | T10: Master's usually required | U10: The Faculty of Applied Sciences (TNW) houses the applied-physics departments (e.g. Quantum Nanoscience, Imaging Physics, Radiation Science & Technology, Bionanoscience). TU Delft lists a PhD tuition fee of EUR 11,000 per PhD programme plus an annual bench fee. The bench fee is charged to the institute you work for, or to you if no institute funds you. Who pays is agreed at the start, and the faculty may waive either fee. Teaching is capped at 20% of the appointment. | V10: https://www.tudelft.nl/en/faculty-of-applied-sciences/research/phd | W10: 2026-10-21
A11: Durham | B11: Durham University · Department of Physics | C11: United Kingdom | D11: England | E11: 46371 | F11: Departmental deadline Dec 15, 2026: applications by then get full consideration for all scholarships and funding. Later applications are still considered, but may be eligible only for some scholarships. There is no set deadline for admission itself. | G11: Not stated | I11: Not stated | J11: Not stated on the page checked | K11: Not stated | L11: Not stated | M11: 4.5 (new scale) | N11: No | O11: Exemption needs at least 1 full academic year of a degree studied in the UK or another majority English-speaking country (within 2 years of the start), or a UK-degree-equivalent qualification from (or nationality of) a listed country. India is not on the list. Physics may interview you without a test certificate, but still requires one. | P11: Recommended | Q11: University guidance says to contact a potential supervisor before applying. Physics lets you apply to a research area and list the staff you would like to consider your application, and does not state that prior agreement is required. | R11: Competitive | S11: Funded studentships (UK Research Councils, external sponsors, Durham) are typically available in all research areas; apply by Dec 15, 2026 for full consideration for all scholarships and funding | T11: Either | U11: The department advises not submitting before mid-October because a new admissions system has just gone live. One application covers several projects or research areas. | V11: https://www.durham.ac.uk/departments/academic/physics/postgraduate-study/research-degrees/how-to-apply/ | W11: 2026-10-21
A12: EPFL | B12: EPFL (École polytechnique fédérale de Lausanne) · Doctoral Program in Physics (EDPY) | C12: Switzerland | D12: Vaud (Lausanne) | E12: 46507 | F12: Two rounds a year: October 31 and April 30. Next: Oct 31, 2026 (imminent) and Apr 30, 2027. Complete files incl. 3 letters. Years inferred. | G12: 0 | I12: No fee | J12: Not needed: no application fee | K12: Recommended | L12: Not stated | M12: Not stated | N12: Yes | O12: No English test is strictly required; proficiency in English is required and TOEFL is strongly recommended | P12: Required | Q12: Admission = eligible by committee AND a thesis advisor offers you a PhD position after interview; eligible files are shared with all thesis directors | R12: Guaranteed | S12: Enrolment requires secured funding; lab-appointed doctoral students get an employment contract | T12: Master's usually required | U12: French not required to start; visas/work permits take about 3 months after appointment. | V12: https://www.epfl.ch/education/phd/edpy-physics/edpy-how-to-apply/ | W12: 2026-10-21
A13: ETH Zurich | B13: ETH Zurich · Department of Physics (D-PHYS) | C13: Switzerland | D13: Zurich | E13: Per position | F13: No central deadline: each professor recruits their own doctoral students; some posts are advertised as vacancies | G13: Not stated | I13: Not stated | J13: Not stated on the page checked | K13: Not stated | L13: Not stated | M13: Not stated | N13: Not stated | O13: Not stated on the page checked; ask the professor | P13: Required | Q13: A professor must agree to supervise you; contact professorships directly (the Doctoral Administration does not match candidates) | R13: Typical | S13: With few exceptions doctorates are linked to a position (employment) at ETH or in the ETH Domain | T13: Not stated | U13: Individual doctorate model: no overarching doctoral school. See the AVETH survival guide linked from the page. | V13: https://ethz.ch/en/doctorate/finding-a-place.html | W13: 2026-10-21
A14: Georgia Tech | B14: Georgia Institute of Technology · School of Physics | C14: USA | D14: Georgia | E14: 46371 | F14: December 15. Year inferred for Fall 2027. | G14: 105 | H14: USD | I14: Limited | J14: Institute waivers for outstanding undergraduate achievement or recruitment events; internationals must submit ALL materials (incl. English scores) before requesting | K14: Not required | L14: Not required | M14: 106 | N14: No | O14: All applicants must demonstrate English proficiency at application, regardless of citizenship | P14: Not stated | Q14: No pre-application supervisor requirement mentioned | R14: Not stated | S14: PhD support terms not stated (MS students get no support) | T14: Direct from bachelor's | U14: Very high English-test thresholds: plan test dates early. | V14: https://physics.gatech.edu/academics/graduate/admissions-info | W14: 2026-10-21
A15: Harvard University | B15: Harvard University · Department of Physics (Harvard Kenneth C. Griffin GSAS) | C15: USA | D15: Massachusetts | E15: 46371 | F15: December 15, 2026 at 05:00 pm (PhD) | G15: 105 | H15: USD | I15: Not stated | J15: A waiver exists; eligibility is decided by questions inside the application fee section. Whether international applicants qualify is not stated. | K15: Optional | L15: Required | M15: 95 | N15: Yes | O15: Exempt if your undergraduate degree is from an institution where English is the primary language of instruction; a master's or other graduate degree does not count | P15: Not stated | Q15: No pre-application supervisor requirement mentioned | R15: Guaranteed | S15: Guaranteed funding for the first five years for all PhD students | T15: Direct from bachelor's | U15: Department site (physics.harvard.edu) blocked automated fetches (403), so facts come from Harvard Griffin GSAS pages. GSAS accepts up to three applications per year to different programs, each with its own fee. | V15: https://gsas.harvard.edu/program/physics | W15: 2026-10-21
A16: Heidelberg (HGSFP) | B16: Heidelberg University · Heidelberg Graduate School for Physics (HGSFP) | C16: Germany | D16: Baden-Württemberg | E16: 46327 | F16: Application portal deadline November 1 (for international students and anyone without prior funding). Year inferred: Nov 1, 2026. | G16: Not stated | I16: Not stated | J16: Not stated on the pages checked | K16: Not stated | L16: Not stated | M16: Not stated | N16: Not stated | O16: Not stated on the pages checked | P16: Not required | Q16: Two routes: the web portal (international students, or anyone without funding) or direct application with an advisor and funding already arranged | R16: Not stated | S16: The portal route is for applicants without prior financial support; funding terms are not stated on the pages checked | T16: Master's usually required | U16: Degree awarded: Dr. rer. nat. | V16: https://hgsfp.physik.uni-heidelberg.de/howtoapply#start | W16: 2026-10-21
A17: IMPRS Astronomy (Heidelberg) | B17: Heidelberg University and Max Planck Institute for Astronomy (MPIA) · IMPRS for Astronomy and Cosmic Physics (IMPRS-HD) | C17: Germany | D17: Baden-Württemberg | E17: 46329 | F17: Nov 3, 2026, 14:00 CET for fall 2027 entry; the application and both reference letters must arrive by then. Interviews Feb 1–5, 2027 | G17: Not stated | I17: Not stated | J17: Not stated on the page checked | K17: Not stated | L17: Not stated | M17: Not stated | N17: Yes | O17: No English test required; communication skills are checked at interview (optional proof may help non-native speakers) | P17: Not required | Q17: A central committee screens applications; shortlisted files go to all potential supervisors and an interested supervisor triggers an interview. The project supervisor makes the final offer | R17: Guaranteed | S17: Official offers come with funding, typically a 3+1-year contract; MSc holders get about EUR 1,800–2,000 net/month (amount and terms depend on the funding source) | T17: Master's usually required | U17: Dr. rer. nat. in astrophysics; six Heidelberg institutes (MPIA, MPIK, ARI, LSW, ITA, HITS). Admitted students register with the Department of Physics and Astronomy via HGSFP. Use reference number IMPRS2027 in the application system. Germany requires a grade of 2.0 or better (about B+). | V17: https://www.imprs-hd.mpg.de/3192/Application | W17: 2026-10-21
A18: ICFO (Barcelona) | B18: ICFO – The Institute of Photonic Sciences · PhD in Photonics (with UPC Doctoral School) | C18: Spain | D18: Catalonia (Castelldefels, Barcelona) | E18: Per position | F18: Apply only through calls/openings on ICFOjobs, each with its own deadline. No PhD call was open on 2026-10-21; candidates may contact group leaders meanwhile. | G18: Not stated | I18: Not stated | J18: Not stated on the page checked | K18: Not stated | L18: Not stated | M18: Not stated | N18: Not stated | O18: No English test or waiver rule stated on the page checked | P18: Required | Q18: Admission needs a pass from the admissions committee after interview AND an offer from at least one host research group with confirmed fellowship funding | R18: Guaranteed | S18: All admitted students are fully funded through (competitive) fellowships for the whole PhD; fellowships cover a 6-month trainee period plus a 4-year PhD period | T18: Master's usually required | U18: Photonics PhD awarded with UPC. Selection: eligibility and admissibility checks, committee evaluation, on-site interviews; under 10% of applicants admitted. Applicants who already hold a PhD are not eligible. Self-funded or external fellowships (e.g. LaCaixa INPhINIT) are also possible. | V18: https://www.icfo.eu/studies/phd-program/ | W18: 2026-10-21
A19: Imperial College London | B19: Imperial College London · Department of Physics | C19: United Kingdom | D19: England | E19: 46328 | F19: President's PhD Scholarship (college-wide, open to all nationalities) rounds: apply by Nov 2, 2026, Jan 11, 2027 or Mar 1, 2027 (23:59 UK time). Physics accepts PhD applications all year; the Theory group lists a Feb 1 deadline 'each year' (shown with the 2026 date). | G19: 0 | I19: No fee | J19: PhD applications carry no application fee, so no waiver is needed | K19: Not stated | L19: Not stated | M19: Not stated | N19: No | O19: Exempt only with a UK-degree-equivalent qualification from a listed country (Australia, Canada, Guyana, Ireland, Malta, New Zealand, South Africa, UK, USA, West Indies); India is not listed | P19: Not required | Q19: Not needed before applying: the Theory group says you need not contact a supervisor, and the Matter community considers you for all available projects. Naming a preferred supervisor helps route your application (Light community). Exception: President's PhD Scholarship applicants must already have a supervisor who has agreed to supervise them. | R19: Competitive | S19: A limited number of fully funded studentships (fees and living costs). Studentships for overseas applicants are very restricted: most overseas students bring home-country scholarships or self-fund (Matter community page). President's PhD Scholarships are open to all nationalities but very competitive. | T19: Direct from bachelor's | U19: There is no single Physics PhD course page; details come from the research-community pages (Light, Matter, Theory), and several still show 2026-cycle dates. Imperial's English levels are TOEFL 92 (Standard) or 100 (Higher), or 4.5/5.0 on the new scale. | V19: https://www.imperial.ac.uk/natural-sciences/departments/physics/students/postgraduate-admissions/phd-opportunities/ | W19: 2026-10-21
A20: Indiana University Bloomington | B20: Indiana University Bloomington · Department of Physics | C20: USA | D20: Indiana | E20: 46371 | F20: December 15 (year inferred); international documents must be received by then. Later applications considered only if positions remain. Dept also calls Dec 15 the priority date. | G20: 70 | H20: USD | I20: None | J20: Department states no fee waivers are granted | K20: Optional | L20: Recommended | M20: 80 | N20: No | O20: No exemption route shown for graduate applicants: non-native speakers may be required to test regardless of where educated, and all non-native speakers seeking any financial aid must submit TOEFL/IELTS/Duolingo | P20: Not stated | Q20: Not stated on the page checked | R20: Typical | S20: PhD package typically provides full funding (TA/RA stipend plus tuition waiver covering most tuition) | T20: Not stated | U20: Domestic-applications page lists graduation from a recognized four-year college and GPA 3.0 on transcripts. Separate Astrophysics, Chemical Physics and Mathematical Physics PhDs exist. | V20: https://physics.indiana.edu/graduate/how-to-apply/international-applications.html | W20: 2026-10-21
A21: Johns Hopkins University | B21: Johns Hopkins University · William H. Miller III Department of Physics & Astronomy | C21: USA | D21: Maryland | E21: 46371 | F21: December 15 preceding September entry; year inferred. Vivien Thomas Scholars Initiative applicants must submit by Dec 1. | G21: 75 | H21: USD | I21: Not stated | J21: Page says the fee may be waived but gives no criteria; international eligibility not stated (JHU graduate admissions site blocked automated fetches) | K21: Optional | L21: Optional | M21: 100 | N21: Not stated | O21: Page requires TOEFL or IELTS for international students; exemption rules not shown on the page checked | P21: Not stated | Q21: No pre-application supervisor requirement mentioned | R21: Guaranteed | S21: All graduate students are appointed as TAs or RAs, which provide tuition, stipend and benefits | T21: Direct from bachelor's | U21: JHU graduate admissions and Krieger school sites blocked automated fetches (403). Admitted PhD students can apply for a $1,500 need-based relocation grant. | V21: https://physics-astronomy.jhu.edu/graduate/admissions/ | W21: 2026-10-21
A22: KTH Stockholm | B22: KTH Royal Institute of Technology · Doctoral Programme in Physics, School of Engineering Sciences (SCI) | C22: Sweden | D22: Stockholm | E22: Per position | F22: No central deadline: apply to an advertised doctoral position; KTH announces positions nine times a year (Feb-Jun, Sep-Dec), each with its own deadline | G22: Not stated | I22: Not stated | J22: Not stated on the page checked | K22: Not stated | L22: Not stated | M22: 90 | N22: Conditional | O22: Indian upper-secondary English can meet the requirement: CBSE (2008 onwards) or CISCE Class XII English grades, or an English-medium upper secondary certificate. The India page offers no degree-based route, so otherwise take a test | P22: Required | Q22: You apply to a specific advertised position; the final admission decision is made by the head of school in consultation with the intended supervisors | R22: Guaranteed | S22: People admitted to advertised positions are employed by KTH on a monthly salary, currently starting at SEK 33,000 and rising to SEK 37,100 per month | T22: Master's usually required | U22: KTH's Doctoral Program in Physics (School of Engineering Sciences) has six specialisations; the application rules are KTH-wide. A PhD is four years full-time, with up to 20% departmental duties. English rules point to University Admissions in Sweden (universityadmissions.se), which KTH links to; its India rules are written for master's admission and KTH says the doctoral requirement is the same. | V22: https://www.kth.se/en/sci/utbildning/forskarutbildning/forskaramnet-fysik-1.795636 | W22: 2026-10-21
A23: Munich (MCQST) | B23: LMU / TUM / Max Planck (Munich) · MCQST Doctoral Fellowships in Quantum Science & Technology (formerly IMPRS-QST) | C23: Germany | D23: Bavaria (Munich) | E23: Not stated | F23: Call opens October 2026 for Fall 2027; deadline not yet published on the page checked | G23: Not stated | I23: Not stated | J23: Not stated on the page checked | K23: Not stated | L23: Not stated | M23: Not stated | N23: Not stated | O23: Not stated | P23: Not stated | Q23: Not stated on the page checked | R23: Not stated | S23: Doctoral fellowships; terms not stated on the page checked | T23: Not stated | U23: One shared platform: apply for the MCQST fellowship, the Munich Quantum Valley (MQV) fellowship, or both. IMPRS-QST no longer runs a separate program. | V23: https://www.imprs-quantum.mpg.de/3192/Application | W23: 2026-10-21
A24: Leiden | B24: Leiden University · Leiden Institute of Physics (LION) | C24: Netherlands | D24: South Holland (Leiden) | E24: Per position | F24: Paid PhD positions are advertised as vacancies with their own deadlines | G24: Not stated | I24: Not stated | J24: Not stated on the pages checked | K24: Not stated | L24: Not stated | M24: Not stated | N24: Not stated | O24: Not stated on the pages checked (theses are written in English) | P24: Required | Q24: Apply to a specific advertised position; requirements are set with the thesis supervisor | R24: Guaranteed | S24: All LION PhD projects are 4-year fully paid positions (usually a 1+3-year contract) with about 10% teaching | T24: Master's usually required | U24: Self-funded entry possible with grants covering living costs and a bench fee. | V24: https://www.universiteitleiden.nl/en/science/physics/phd-programme | W24: 2026-10-21
A25: Massachusetts Institute of Technology | B25: Massachusetts Institute of Technology · Department of Physics | C25: USA | D25: Massachusetts | E25: 46371 | F25: December 15 at 11:59 PM Eastern (application opens September 15); year inferred | G25: 90 | H25: USD | I25: Limited | J25: International applicants qualify only if currently at a US college AND in a select research-preparation program; no hardship-only waivers for internationals. Requests due Dec 1 for Dec 15 deadlines. | K25: Recommended | L25: Recommended | M25: 100 | N25: No | O25: Automatic exemption only for undergraduate degrees from Australia, Canada, Ireland, New Zealand, UK or US; English-medium degrees from other countries (e.g. India) explicitly do not qualify. Physics says a department waiver "may be available" (discretionary, requested in the application). | P25: Not stated | Q25: No pre-application supervisor requirement mentioned | R25: Guaranteed | S25: PhD students fully supported for the whole program, given satisfactory progress (tuition, health insurance, stipend) | T25: Not stated | U25: physics.mit.edu blocked automated fetches (403, also with a headless browser), so facts come from the MIT Office of Graduate Education program page. OGE grants up to three fee waivers per applicant. | V25: https://oge.mit.edu/programs/physics/ | W25: 2026-10-21
A26: IMPRS Quantum Materials (Dresden) | B26: Max Planck Institute for Chemical Physics of Solids (MPI CPfS) and TU Dresden · IMPRS for Chemistry and Physics of Quantum Materials (IMPRS-CPQM) | C26: Germany | D26: Saxony | E26: 46356 | F26: Nov 30, 2026 for the 2026/27 recruitment cycle (selection workshop in Dresden Feb 22–24, 2027; start by Sept 2027). Applications outside the cycle are accepted year-round and handled individually | G26: 0 | I26: No fee | J26: Not needed: no application fee | K26: Not stated | L26: Not stated | M26: Not stated | N26: Conditional | O26: No English certificate is generally needed; the exception is projects involving the University of St Andrews, which requires evidence of English proficiency | P26: Not required | Q26: Central application via the online form; do not send applications to individual PIs. Project supervisors and a PI team review applications | R26: Guaranteed | S26: All students are supported: in Germany on the standard Max Planck PhD contract; in the UK at the national stipend rate, with St Andrews tuition covered | T26: Either | U26: Tri-institutional with the University of St Andrews; which university you register at depends on your entry qualifications, home country and project. Choose from the listed projects; own research proposals are not accepted. | V26: https://imprs-cpqm.mpg.de/apply-now | W26: 2026-10-21
A27: IMPRS Quantum Dynamics (Heidelberg) | B27: Max Planck Institute for Nuclear Physics (MPIK) and Heidelberg University · IMPRS for Quantum Dynamics in Physics, Chemistry and Biology (IMPRS-QD) | C27: Germany | D27: Baden-Württemberg | E27: 46327 | F27: Nov 1, 2026 for the 2026/2027 winter round (complete applications including reference letters) | G27: Not stated | I27: Not stated | J27: Not stated on the page checked | K27: Not stated | L27: Not stated | M27: Not stated | N27: Not stated | O27: Proof of English required if your mother tongue is not English or German; the page does not say whether an English-medium degree counts | P27: Not stated | Q27: No pre-application supervisor rule stated; short-listed candidates interview with their potential supervisors | R27: Competitive | S27: The school offers funding to selected students worldwide; admission is competitive and living-expense funding needs approval by the full IMPRS-QD Board | T27: Master's usually required | U27: Partners: MPIK, Heidelberg University, DKFZ, MPI for Medical Research, GSI Darmstadt. Physics students funded by IMPRS-QD are expected to join HGSFP; the online application link goes to the HGSFP portal. | V27: https://www.mpi-hd.mpg.de/imprs-qd/application/ | W27: 2026-10-21
A28: IMPRS Solar System (Göttingen) | B28: Max Planck Institute for Solar System Research (MPS), with University of Göttingen and TU Braunschweig · IMPRS for Solar System Science (Solar System School) | C28: Germany | D28: Lower Saxony | E28: Rolling | F28: Apply any time for advertised open projects; applications are reviewed in several rounds a year. The 2025/26 call rounds closed Feb 1, Jun 1 and Oct 1, 2026; dates for the next rounds were not yet published when checked | G28: Not stated | I28: Not stated | J28: Not stated on the page checked | K28: Not required | L28: Recommended | M28: Not stated | N28: Yes | O28: A degree from a course of study taught in English counts as proof of English; a test is needed only if your recent education was not in English or German for at least two years | P28: Not required | Q28: Contacting faculty first is not mandatory (it may help); a committee screens applications and the potential supervisor makes the final decision | R28: Typical | S28: Usually a doctoral support contract at 75% of TVöD E13 (about EUR 2,400 net/month on average); some students are on third-party scholarships. The 2025/26 call offered successful applicants a 3.5-year contract plus wrap-up funding | T28: Master's usually required | U28: Solar/stellar physics, planetary science and geoscience projects; choose up to three advertised open projects. Degree awarded by University of Göttingen or TU Braunschweig. The funding page says three-year contracts; the call and FAQ say 3.5 years. | V28: https://www.mps.mpg.de/phd/application | W28: 2026-10-21
A29: McGill | B29: McGill University · Department of Physics | C29: Canada | D29: Quebec | E29: 46371 | F29: December 15 for September (Fall) admission, international and domestic. Year inferred for Fall 2027. | G29: 120.99 | H29: CAD | I29: Not stated | J29: No waiver route stated on the pages checked | K29: Optional | L29: Recommended | M29: 86 | N29: Yes | O29: Normally exempt with a degree from a recognized foreign institution where English is the language of instruction; send proof to the department | P29: Recommended | Q29: Not required, but highly recommended: professors select students for their groups | R29: Guaranteed | S29: All graduate students receive a standard stipend, plus possible TA work | T29: Master's usually required | U29: The department FAQ answers 'Do I need to speak French?'; read it before applying. A Winter (January) intake also exists. | V29: https://www.physics.mcgill.ca/grads/application.html | W29: 2026-10-21
A30: McMaster | B30: McMaster University · Physics and Astronomy | C30: Canada | D30: Ontario | E30: 46419 | F30: No formal deadline (rolling, offers while funding lasts); international applicants strongly encouraged to apply by February 1 for internal scholarships. SGS: complete by January 31 for full scholarship consideration; considered until April 30. | G30: 150 | H30: CAD | I30: Not stated | J30: No waiver route stated on the pages checked | K30: Not stated | L30: Not stated | M30: Not stated | N30: Conditional | O30: The application asks whether your degree's official language of instruction AND evaluation was English; programs may add their own requirements | P30: Recommended | Q30: Funding includes a research fellowship from the supervisor's grant; contact faculty directly to ask if they are taking students | R30: Guaranteed | S30: Full support guaranteed for all admitted students (scholarship + supervisor research scholarship + TA); minimum at least CAD 21,000 after tuition and fees | T30: Not stated | U30: About 25 new MSc/PhD students per year; first offers often go out before Christmas, so earlier is better. | V30: https://physics.mcmaster.ca/graduate-studies/how-to-apply/ | W30: 2026-10-21
A31: North Carolina State University | B31: North Carolina State University · Department of Physics and Astronomy | C31: USA | D31: North Carolina | E31: 46391 | F31: Priority deadline January 4, 2027 for Fall 2027; in exceptional cases international applications accepted until March 1 | G31: 95 | H31: USD | I31: Domestic only | J31: Waiver only for the first 100 U.S.-citizen applicants with GPA above 3.0; department does not waive the fee for international students | K31: Optional | L31: Optional | M31: 80 | N31: Not stated | O31: Exempt if a citizen of a country where English is an official language and the language of instruction in higher education (FAQ says "the official language"); no country list on the pages checked, so India's status is not confirmed. Medium-of-instruction letters not mentioned. | P31: Not stated | Q31: Not stated on the page checked (candidate statement should list possible advisers) | R31: Typical | S31: Admits usually offered support; over 95% of students on TA/RA/fellowship (~$30,000/yr in Fall 2026) | T31: Direct from bachelor's | U31: International applicants are usually interviewed by Skype or phone. TA eligibility needs the SPEAK test plus higher IELTS speaking (7.0) or Duolingo sub-scores (125). Graduate School site (grad.ncsu.edu) could not be fetched (TLS failure). | V31: https://physics.sciences.ncsu.edu/graduate/apply/ | W31: 2026-10-21
A32: Penn State | B32: Penn State University (University Park) · Department of Physics | C32: USA | D32: Pennsylvania | E32: 46402 | F32: January 15 (applications for Fall 2027 open October 1, 2026). Year inferred. | G32: 0 | I32: Available | J32: Automatic for everyone this cycle via code PHYS2027 (international included) | K32: Not stated | L32: Not stated | M32: Not stated | N32: Not stated | O32: Rule is country-based ('non-English speaking countries'); exemption list not shown on the page checked | P32: Not stated | Q32: No pre-application supervisor requirement mentioned | R32: Not stated | S32: Not stated on the page checked | T32: Not stated | U32: Free to apply this cycle; a low-cost 'safety-to-target' add for many lists. | V32: https://science.psu.edu/physics/graduate/applying | W32: 2026-10-21
A33: Purdue | B33: Purdue University (West Lafayette) · Physics and Astronomy | C33: USA | D33: Indiana | E33: 46371 | F33: December 15 for fall, including TOEFL/IELTS scores. Year inferred for Fall 2027. | G33: 75 | H33: USD | I33: Limited | J33: Fee-waiver applications exist through Big Ten and Purdue; check eligibility for international applicants | K33: Optional | L33: Optional | M33: Not stated | N33: Not stated | O33: Exemption rules not shown on the pages checked | P33: Not stated | Q33: No pre-application supervisor requirement mentioned | R33: Typical | S33: Most common support is a half-time (20 h/week) teaching assistantship; tick the box on the main application | T33: Not stated | U33: Purdue states that from August 15, 2026, Indiana law requires additional review steps for some international applicants. Oral English certification is required to keep a TA appointment for non-native speakers. | V33: https://www.physics.purdue.edu/academic-programs/future_students/admissions.html | W33: 2026-10-21
A34: Queen's | B34: Queen's University · Physics, Engineering Physics and Astronomy | C34: Canada | D34: Ontario | E34: 46394 | F34: January 7 for full consideration (September start); rolling review so apply early. Year inferred. | G34: Not stated | I34: Not stated | J34: Not stated on the pages checked | K34: Optional | L34: Optional | M34: Not stated | N34: Conditional | O34: You may REQUEST an exemption if, in the 12 months before applying, you studied 1+ full year at a post-secondary institution where English is the official language of instruction | P34: Recommended | Q34: A complete application needs a research proposal; work with a potential supervisor early | R34: Guaranteed | S34: Minimum stipend guaranteed; PhD for four years (TA ~10 h/week in fall/winter contributes) | T34: Master's usually required | U34: Research proposal required. OGS applications due March 1. | V34: https://www.queensu.ca/physics/grad-studies/applicants | W34: 2026-10-21
A35: Rice | B35: Rice University · Physics and Astronomy | C35: USA | D35: Texas | E35: 46371 | F35: December 15, 2026, 11:59 EST; late applications considered until April 1, 2027 (less competitive) | G35: 85 | H35: USD | I35: Available | J35: Doctoral Fee Waiver Weeks open to students worldwide Oct 14-Nov 1, 2026 (or until waivers run out); completed application due Nov 27. Also waived for Texas/neighbouring-state students, GCURS speakers, Fulbright Scholars. | K35: Not considered | L35: Not considered | M35: 90 | N35: Not stated | O35: Exemption rules not shown on the department page checked | P35: Not stated | Q35: No pre-application supervisor requirement mentioned | R35: Not stated | S35: Not stated on the page checked | T35: Not stated | U35: Applied Physics is a separate Rice program with its own deadline and fee policy. | V35: https://physics.rice.edu/how-apply | W35: 2026-10-21
A36: Rutgers | B36: Rutgers University (New Brunswick) · Physics and Astronomy | C36: USA | D36: New Jersey | E36: 46388 | F36: Submit everything before January 1 for full financial-aid consideration (fall). Year inferred. | G36: Not stated | I36: Limited | J36: SGS auto-waives for certain groups; department can waive for a few applicants each year, usually used up months before the deadline - ask early | K36: Recommended | L36: Recommended | M36: Not stated | N36: Yes | O36: Exempt with 3+ years of undergraduate study or a master's where the mode of instruction was English | P36: Not stated | Q36: No pre-application supervisor requirement mentioned | R36: Guaranteed | S36: Department generally guarantees PhD support for 5 years | T36: Not stated | U36: Final decisions generally before April 15 for complete applications received by January. | V36: https://physics.rutgers.edu/academics/graduate-program/admissions | W36: 2026-10-21
A37: SISSA | B37: SISSA (Trieste) · PhD in Theory and Numerical Simulation of Condensed Matter | C37: Italy | D37: Friuli-Venezia Giulia (Trieste) | E37: Not stated | F37: Spring call closes early March each year (exact date in the call); a second call in September only if places remain. 2027 call not yet published. | G37: Not stated | I37: Not stated | J37: Not stated on the page checked | K37: Not stated | L37: Not stated | M37: Not stated | N37: Not stated | O37: Not stated on the page checked | P37: Not stated | Q37: Selection is a competition (qualifications, written exam, interview); no prior supervisor requirement mentioned | R37: Not stated | S37: Not stated on the page checked | T37: Not stated | U37: SISSA can contribute up to EUR 150 toward travel for the exams. Each SISSA physics group runs its own call and exam; this record covers Condensed Matter only. | V37: https://cm.sissa.it/phd/admission | W37: 2026-10-21
A38: SFU | B38: Simon Fraser University · Department of Physics | C38: Canada | D38: British Columbia | E38: 46402 | F38: Apply before January 15 (better chance at desired group and awards); system open until May 31. Year inferred. | G38: 150 | H38: CAD | I38: Not stated | J38: Not stated on the pages checked | K38: Not stated | L38: Not stated | M38: Not stated | N38: No | O38: Exempt only if BOTH: degree taught and examined in English AND institution in an English-primary country (list linked); otherwise submit scores | P38: Not stated | Q38: Not stated in the text checked; transfers need supervisory committee approval | R38: Not stated | S38: Not stated on the pages checked | T38: Master's usually required | U38: PhD starts possible in September, January or May. | V38: https://www.sfu.ca/physics/graduate/prospective/applying.html | W38: 2026-10-21
A39: Stanford | B39: Stanford University · Department of Physics | C39: USA | D39: California | E39: 46370 | F39: 11:59pm PST, December 14, 2026 (no late applications); Knight-Hennessy applicants: physics application by December 1, 2026 | G39: Not stated | I39: Limited | J39: Some applicants may qualify; see Stanford Graduate Admissions fee-waiver page for eligibility | K39: Required | L39: Required | M39: Not stated | N39: Yes | O39: Not required if your degree (or international equivalent) is from a university where ALL instruction was in English; no documents needed at application | P39: Not stated | Q39: No pre-application supervisor requirement mentioned (you choose theory/experiment/astro area) | R39: Guaranteed | S39: Department provides financial support for all enrolled students | T39: Not stated | U39: Two GRE requirements make Stanford one of the most test-heavy programs this cycle. | V39: https://physics.stanford.edu/graduate/graduate-admissions | W39: 2026-10-21
A40: Stockholm | B40: Stockholm University · Department of Physics (Fysikum) | C40: Sweden | D40: Stockholm | E40: Per position | F40: No central deadline: positions are advertised on the department vacancies page about four times a year (normally Feb, Apr, Sep, Oct), each with its own deadline. The page lists only 2025 dates | G40: Not stated | I40: Not stated | J40: Not stated on the page checked | K40: Not stated | L40: Not stated | M40: 79 | N40: Yes | O40: A previously completed university degree taught in English is listed as meeting the English requirement (as an alternative to IELTS/TOEFL) | P40: Required | Q40: You apply to a specific advertised position and are assessed against the other applicants for it; at least two supervisors are appointed in connection with admission | R40: Guaranteed | S40: Funding for the whole study period (normally 4 years) is a condition of admission; in most cases you are employed as a PhD student with a salary | T40: Master's usually required | U40: Fysikum's doctoral subjects are Physics, Theoretical Physics, Chemical Physics and Medical Radiation Physics. Applicants not known from SU undergraduate studies normally have to show their qualifications by taking one or two advanced-level courses or doing a suitable project (eligibility page). The call dates on the page are for 2025; check the department vacancies page for the 2026-27 calls. | V40: https://www.su.se/english/divisions/department-of-physics/education/courses-and-programmes/doctoral-studies-at-the-department-of-physics | W40: 2026-10-21
A41: Stony Brook | B41: Stony Brook University (SUNY) · Physics and Astronomy | C41: USA | D41: New York | E41: 46371 | F41: One strict deadline: December 15 (PhD and MSI, Fall). Year inferred. | G41: 100 | H41: USD | I41: Domestic only | J41: Graduate School waivers for domestic (US) applicants; a separate department program covers fees for Latin American applicants | K41: Not considered | L41: Not considered | M41: 5 (new scale) | N41: Yes | O41: Exemption examples include a degree from an English-instruction institution | P41: Not stated | Q41: No pre-application supervisor requirement mentioned | R41: Guaranteed | S41: Full support for the duration; 9-month TA stipend USD 30,000 (+8,000 summer TA); RA salary 41,000 (2026) | T41: Not stated | U41: Decisions only after December 15; offers must be accepted by April 15. | V41: https://www.stonybrook.edu/physics/graduate/apply.html | W41: 2026-10-21
A42: TU Munich | B42: Technical University of Munich (TUM) · Doctorate in Physics (TUM School of Natural Sciences; TUM Graduate School rules) | C42: Germany | D42: Bavaria | E42: Per position | F42: No central application or deadline: apply to advertised research-associate positions (TUM job portal or chair websites) or directly to a potential supervisor | G42: Not stated | I42: Not stated | J42: Not stated on the page checked | K42: Not stated | L42: Not stated | M42: Not stated | N42: Yes | O42: No formal language requirement for doctoral admission at TUM level (very good English expected); individual job ads may set their own language requirements | P42: Required | Q42: Finding a TUM supervisor is the first and mandatory step; degree recognition happens only after a professor agrees | R42: Typical | S42: The most common route is a salaried research-associate position; self-initiative applicants usually need their own funding (e.g. an external scholarship). No tuition fees | T42: Master's usually required | U42: Individual doctorate model with no physics-specific call; rules quoted are TUM-wide (TUM Graduate School). Physics doctorates are handled by the TUM School of Natural Sciences (promotion@nat.tum.de). | V42: https://www.gs.tum.de/en/gs/path-to-a-doctorate/application/requirements/ | W42: 2026-10-21
A43: Texas A&M | B43: Texas A&M University · Physics and Astronomy | C43: USA | D43: Texas | E43: 46397 | F43: January 10, 2027 (later applications accepted but processed after) | G43: 114 | H43: USD | I43: Domestic only | J43: Automatic waiver for Pell Grant or McNair recipients (U.S. programs); no international route stated on the pages checked | K43: Optional | L43: Optional | M43: Not stated | N43: Not stated | O43: Not stated on the pages checked | P43: Not stated | Q43: No pre-application supervisor requirement mentioned | R43: Not stated | S43: Not stated on the pages checked | T43: Not stated | U43: Physics and Astronomy use separate application forms. Decisions must be returned by April 15. | V43: https://artsci.tamu.edu/physics-astronomy/academics/prospective-graduates/how-to-apply.html | W43: 2026-10-21
A44: Ohio State | B44: The Ohio State University · Department of Physics | C44: USA | D44: Ohio | E44: 46356 | F44: Best consideration: November 30 (international) or December 15 (domestic); December 1 for automatic fellowship nomination; late applications until April 14 with much less funding. Years inferred. | G44: 70 | H44: USD | I44: Limited | J44: Extremely limited; same criteria for international and domestic; based on alignment with the department's mission; none for late submissions | K44: Optional | L44: Optional | M44: Not stated | N44: No | O44: Exempt only by citizenship of, or a bachelor's from, a listed country; English-taught courses alone do not exempt you | P44: Not stated | Q44: No pre-application supervisor requirement mentioned | R44: Typical | S44: TA/RA appointments include a monthly stipend and full tuition and general-fee waiver; RA stipend equals TA stipend | T44: Direct from bachelor's | U44: International applicants need a four-year degree (Higher National Diplomas excluded). | V44: https://physics.osu.edu/graduate/prospective-students | W44: 2026-10-21
A45: Trinity College Dublin | B45: Trinity College Dublin · School of Physics (PhD by research) | C45: Ireland | D45: Leinster (Dublin) | E45: Rolling | F45: No closing date for research degrees; two registration periods (1 September and 1 March), most start in September. Apply early: supervisory capacity is limited. Funded project adverts set their own deadlines. | G45: Not stated | I45: None | J45: Application fee cannot be waived | K45: Not stated | L45: Not stated | M45: 90 | N45: Conditional | O45: PG applicants whose primary degree was taught through English may request an exemption, with a formal letter from the awarding institution stating the degree was delivered wholly in English; the course director must approve, then Admissions considers it | P45: Required | Q45: Get a potential supervisor's approval first; the formal application link is sent only after a supervisor offers you a place | R45: Typical | S45: Most students are funded (fees + stipend) by national/international bodies, usually tied to specific projects; unfunded applicants must win funding (e.g. IRC, TCD/School studentships, which are extremely competitive). Some funded adverts are restricted to EU/EEA/UK applicants. | T45: Direct from bachelor's | U45: PhD normally takes about four years; start dates 1 September or 1 March. Funded projects are advertised on the School's postgraduate page (adverts there on 2026-10-21 were from 2024-25). Fee status (EU vs non-EU) affects tuition, so check each advert's eligibility. | V45: https://www.tcd.ie/physics/study/prospective/postgraduate/how-to-apply/ | W45: 2026-10-21
A46: Bonn-Cologne (BCGS) | B46: Universities of Bonn and Cologne · Bonn-Cologne Graduate School of Physics and Astronomy (BCGS) | C46: Germany | D46: North Rhine-Westphalia | E46: Rolling | F46: No PhD deadline: start any time by individual arrangement with a supervisor | G46: Not stated | I46: Not stated | J46: Not stated on the page checked | K46: Not stated | L46: Not stated | M46: Not stated | N46: Not stated | O46: Not stated | P46: Required | Q46: BCGS does not provide PhD positions: find and apply for a PhD position (with a supervisor) at Bonn or Cologne yourself | R46: Not stated | S46: Funding comes with the PhD position you secure; not stated centrally | T46: Not stated | U46: PhD usually 3 years. Look at the University of Bonn and Cologne vacancy pages for advertised positions. | V46: https://www.uni-bonn.de/de/forschung-lehre/early-career/eine-promotion-planen/spps/bigs-physics-and-astronomy | W46: 2026-10-21
A47: Alberta | B47: University of Alberta · Department of Physics | C47: Canada | D47: Alberta | E47: 46357 | F47: December 1 first-round deadline (widest scholarship consideration); January 8 second round; March 31 final date for Fall intake. Years inferred for Fall 2027. | G47: Not stated | I47: None | J47: Department says the fee cannot be waived | K47: Not stated | L47: Not stated | M47: 90 | N47: Conditional | O47: Exempt only if your country or institution is on the FGPS recognized list. For India it lists e.g. IITs (all campuses), IISc, University of Hyderabad, Jadavpur, NIT Calicut; IISERs are NOT listed. Physics will not waive otherwise. | P47: Not stated | Q47: Physics pages do not state a pre-application supervisor requirement; FGPS notes some thesis programs require one | R47: Guaranteed | S47: Minimum CAD 100,000 over years 1-4 and at least CAD 25,000 in year 1 for PhD students (from Fall 2025); department also commits support for normal program duration | T47: Either | U47: Statement of purpose: 500 words max, one page. About 30 graduate admits per year. Committee meets late December, mid-January, late February, late March. | V47: https://www.ualberta.ca/en/physics/graduate-studies/information-for-prospective-students-and-applicants/deadlines.html | W47: 2026-10-21
A48: Amsterdam (UvA) | B48: University of Amsterdam · Institute of Physics (IoP), Faculty of Science | C48: Netherlands | D48: North Holland (Amsterdam) | E48: Per position | F48: No central deadline: apply to an advertised vacancy (each has its own deadline) or send an open application to a research school or supervisor | G48: Not stated | I48: Not stated | J48: Not stated on the page checked | K48: Not stated | L48: Not stated | M48: Not stated | N48: Not stated | O48: Not stated on the page checked | P48: Required | Q48: An authorised supervisor (with the right to award doctorates) must agree to accept you; a second supervisor is always appointed | R48: Typical | S48: Vacancy positions are salaried UvA employment; an open application may come without UvA funding, in which case you need a grant, scholarship, employer or your own money | T48: Master's usually required | U48: These are UvA-wide pages; the Institute of Physics lists its PhD openings through the UvA vacancies site. The admission page requires 'a good command of English' and says a faculty or institute may add language requirements; no test minimum was found. | V48: https://www.uva.nl/en/research/phd/admission-to-a-doctoral-programme/admission-to-a-doctoral-programme.html | W48: 2026-10-21
A49: University of Arizona | B49: University of Arizona · Department of Physics | C49: USA | D49: Arizona | E49: 46357 | F49: December 1, 2026 (applications open October 1, 2026); FAQ says later applications are often still considered | G49: 90 | H49: USD | I49: Limited | J49: Waivers for participants of listed sponsored programs (mostly U.S. schemes such as McNair, TRIO, GEM; list also includes Latin American summer/winter research programs) and need-based waivers on request to the program coordinator with evidence such as U.S. federal grants (Pell); no explicit statement on international eligibility | K49: Optional | L49: Optional | M49: 79 | N49: Yes | O49: Graduate College exempts citizens of countries where English is an official language, and its country table lists India as "test required: No". CONFLICT: the department page literally says proof is required for applicants who "do not hold a degree from a US institution", then defers to the Graduate College country list; confirm with the department. Separately, international TAs from non-English-dominant countries must pass a spoken-English evaluation. | P49: Not required | Q49: Admission is department-wide, not tied to a research group; contacting faculty is not needed to gain admission | R49: Guaranteed | S49: All admitted PhD students guaranteed TA or RA funding for at least the first two years; department strives to continue it with satisfactory progress | T49: Not stated | U49: Graduate College country table lists the minimum degree for India as a 3-year bachelor showing 120 or more credits. Duolingo is not accepted. | V49: https://physics.arizona.edu/graduate-studies/apply-programs/phd-application-procedure | W49: 2026-10-21
A50: Bristol | B50: University of Bristol · School of Physics | C50: United Kingdom | D50: England | E50: 46404 | F50: Funding deadline: applications must be received before Jan 18, 2027 (i.e. by Jan 17) for full consideration for UKRI, University of Bristol or School of Physics funding; apply as soon as possible after the cycle opens in October. Later applications are not considered once the programme is full. | G50: Not stated | I50: Not stated | J50: Not stated on the page checked | K50: Not stated | L50: Not stated | M50: 4.5 (new scale) | N50: Yes | O50: A degree from any country counts if it was fully taught and examined in English, shown by an official Medium of Instruction (MOI) letter from the awarding institution. It must have been awarded no more than 7 years before the start, and the University may still ask for more evidence. | P50: Recommended | Q50: Encouraged to contact the research theme's academic lead or a potential supervisor informally before applying; if you have already contacted one, name them on the form | R50: Competitive | S50: The School's PhD scholarships are awarded competitively; it also typically receives some University of Bristol PGR Scholarships. Applicants bringing home-country, Commonwealth or other scholarships are welcomed. | T50: Master's usually required | U50: The admissions statement linked from the page is still for 2026 entry (the 2027 version is due in the autumn). The University's 2025-26 application-fee policy (a PDF, not machine-checked) lists fees only for Business School and Economics taught programmes. | V50: https://www.bristol.ac.uk/study/postgraduate/research/physics/ | W50: 2026-10-21
A51: UBC | B51: University of British Columbia (Vancouver) · Physics and Astronomy | C51: Canada | D51: British Columbia | E51: 46357 | F51: 1 December 2026 for September 2027 intake | G51: 168.25 | H51: CAD | I51: Limited | J51: Automatic waiver only for citizens AND residents of the UN's 50 least developed countries (India is not on that list) | K51: Not required | L51: Not required | M51: 90 | N51: Yes | O51: Test required only if your university's primary language of instruction is not English (confirm with the program for your institution) | P51: Not required | Q51: Name faculty of interest in the application; no prior commitment needed, but contacting faculty is encouraged | R51: Guaranteed | S51: At least CAD 40,000/year for each of the first four PhD years (from September 2026) | T51: Master's usually required | U51: Application fee is payable by Visa/Mastercard credit or debit (select 'credit card' for debit). Astronomy PhD is a separate listing. | V51: https://www.grad.ubc.ca/prospective-students/graduate-degree-programs/phd-physics | W51: 2026-10-21
A52: Calgary | B52: University of Calgary · Physics and Astronomy | C52: Canada | D52: Alberta | E52: 46402 | F52: January 15 for September admission (Canadian and international); system closes that day. Year inferred. | G52: Not stated | I52: None | J52: No fee-waiver program | K52: Not stated | L52: Required | M52: Not stated | N52: No | O52: Test required if your degree is from a country where English is not a native language (English-taught courses alone do not exempt you) | P52: Required | Q52: No supervisor needed to apply, but you are admitted only if at least one potential supervisor will fund you; contacting faculty first helps | R52: Guaranteed | S52: All admitted full-time thesis students are funded (tuition still payable) | T52: Not stated | U52: First-round offers take at least a month after January 15. | V52: https://grad.ucalgary.ca/future-students/graduate/discover-opportunities/explore-programs/physics-and-astronomy-phd | W52: 2026-10-21
A53: Berkeley | B53: University of California, Berkeley · Department of Physics | C53: USA | D53: California | E53: 46371 | F53: December 15, 2026, 8:59 PM Pacific for Fall 2027; application should be complete incl. letters | G53: Not stated | I53: Domestic only | J53: Graduate Division waivers are for U.S. citizens/permanent residents | K53: Recommended | L53: Required | M53: 90 | N53: No | O53: Exemption depends on the country of your bachelor's institution; India is not on Berkeley's exempt list (a U.S.-accredited institution abroad would qualify) | P53: Not stated | Q53: No pre-application supervisor requirement mentioned | R53: Not stated | S53: Not stated on the admissions page checked | T53: Not stated | U53: Review starts immediately after the deadline; late letters may not be reviewed. Fall grades are not added after December 15. | V53: https://physics.berkeley.edu/academic/graduate-degree/graduate-admissions | W53: 2026-10-21
A54: University of California, Irvine | B54: University of California, Irvine · Department of Physics and Astronomy | C54: USA | D54: California | E54: 46371 | F54: December 15 (year not given; inferred 2026 for Fall 2027); all materials due by the deadline | G54: 155 | H54: USD | I54: Domestic only | J54: International applicants are not eligible for fee waivers (no exceptions); waivers are for U.S. citizens, permanent residents and DACA/AB540 only | K54: Not considered | L54: Not considered | M54: 80 | N54: Conditional | O54: Waived only if your degree-granting institution is listed in WHED with English as the SOLE language of instruction; otherwise a test is required. The same WHED rule exempts from the TA oral-English test. | P54: Not stated | Q54: No pre-application supervisor requirement mentioned | R54: Not stated | S54: Not stated on the pages checked (catalogue lists TA, RA and fellowship support without a guarantee) | T54: Direct from bachelor's | U54: Same application route covers the Chemical and Materials Physics (ChaMP) concentration. International PhD students must be TA-eligible; check the TA oral-English rules. | V54: https://www.physics.uci.edu/apply | W54: 2026-10-21
A55: University of California, Los Angeles | B55: University of California, Los Angeles · Department of Physics and Astronomy | C55: USA | D55: California | E55: 46371 | F55: December 15, 2026 (Fall admission only) | G55: 155 | H55: USD | I55: Limited | J55: Need-based waivers are for U.S. citizens/PRs and others who meet criteria; a non-citizen must be receiving need-based aid from the state of California. Event-based waivers exist for in-person attendees at designated recruitment events (no citizenship rule stated). | K55: Not required | L55: Recommended | M55: 87 | N55: Check tool | O55: Exempt only with a bachelor’s from the U.S. or a country where English is the SOLE language of instruction according to the World Higher Education Database (WHED); the UCLA page lists no countries, so Indian applicants must check WHED (likely not exempt, since India is multilingual) | P55: Not stated | Q55: No pre-application supervisor requirement mentioned; statement of purpose may name potential faculty mentors | R55: Not stated | S55: Not stated on the page checked | T55: Not stated | U55: Department site pa.ucla.edu returned 502 to every fetch; facts are from the UCLA Graduate Education pages. International applicants seeking TA/RA/fellowship support should have one of the three letters comment on their verbal English. | V55: https://grad.ucla.edu/requirements/?app=admission&major=0666 | W55: 2026-10-21
A56: UCSB | B56: University of California, Santa Barbara · Department of Physics | C56: USA | D56: California | E56: 46372 | F56: December 16, 2026, 11:59 PM PST (Fall quarter only) | G56: 155 | H56: USD | I56: Domestic only | J56: Fee waivers are not available to international applicants | K56: Not considered | L56: Not considered | M56: 80 | N56: Not stated | O56: Required if native language is not English; exemptions not shown on the page checked | P56: Recommended | Q56: Strongly encouraged to contact faculty early and list potential advisors | R56: Not stated | S56: Not stated on the page checked | T56: Not stated | U56: IELTS requirement (7.0) is higher than most programs in this list. | V56: https://www.physics.ucsb.edu/academics/graduate/apply | W56: 2026-10-21
A57: Cambridge | B57: University of Cambridge · Department of Physics (Cavendish Laboratory) | C57: United Kingdom | D57: England | E57: 46364 | F57: Course funding deadline Dec 8, 2026 (Gates Cambridge US round Oct 14, 2026). Final application deadline May 13, 2027 for an October 2027 start, but too late for university funding. | G57: 20 | H57: GBP | I57: Limited | J57: A waiver exists for eligible applicants; eligibility criteria not shown on the page checked | K57: Not stated | L57: Not stated | M57: 100 | N57: No | O57: Exemption needs nationality of, or a degree from, a 'majority English-speaking country' (UKVI list); India is not on that list | P57: Recommended | Q57: Some PhD programmes need supervisor contact before applying; a 2027-28 supervisor list is published | R57: Competitive | S57: Not guaranteed: apply by the funding deadline to enter the University funding competition; otherwise secure your own support | T57: Master's usually required | U57: Funding offers start being considered from February; offers of admission from November at the earliest. | V57: https://www.postgraduate.study.cam.ac.uk/courses/directory/pcphpdphy | W57: 2026-10-21
A58: UChicago | B58: University of Chicago · Department of Physics | C58: USA | D58: Illinois | E58: 46370 | F58: December 14, 2026 | G58: 90 | H58: USD | I58: Limited | J58: Specific fee-waiver categories exist (PSD); request through the application portal before paying | K58: Not required | L58: Required | M58: Not stated | N58: Not stated | O58: PSD has waiver criteria; criteria not shown in the text checked | P58: Not stated | Q58: No pre-application supervisor requirement mentioned | R58: Not stated | S58: PhD programs are funded (stipend timing noted); amounts not stated on the pages checked | T58: Not stated | U58: Do not pay the fee before a waiver decision; fees paid before an approved waiver are not refunded (per PSD). | V58: https://physicsrecruitment.psd.uchicago.edu/apply/ | W58: 2026-10-21
A59: University of Colorado Boulder | B59: University of Colorado Boulder · Department of Physics | C59: USA | D59: Colorado | E59: 46357 | F59: December 1, 11:59 PM Eastern (year not printed; inferred 2026 for Fall 2027). Test scores accepted to Dec 15; letters by Dec 15 for priority, not accepted after Jan 1 | G59: 80 | H59: USD | I59: Limited | J59: Department need-based waivers mainly for domestic applicants; for international students only in very exceptional circumstances. Request by November 13, 2026 (decision by Nov 24) and do not submit or pay before the decision. Graduate School waivers are for listed (mostly U.S.) programs. | K59: Not stated | L59: Recommended | M59: 80 | N59: Yes | O59: Citizens of qualifying countries are exempt and India is on the list (the India exception applies only to Engineering Management). MOI letters are not accepted. Applications show the test as required until International Admissions manually waives it. | P59: Not required | Q59: Contacting a potential research advisor before applying or admission is not necessary | R59: Typical | S59: Historically all admitted students (domestic and international) get TA/RA support with tuition and fees covered for the first two years, and satisfactory-progress students are supported after; department says there are no absolute guarantees | T59: Direct from bachelor's | U59: PhD-only admission (no standalone master's). Astrophysical and Planetary Sciences is a separate department with its own application. | V59: https://www.colorado.edu/physics/admissions/graduate-application-information | W59: 2026-10-22
A60: Copenhagen (NBI) | B60: University of Copenhagen · Niels Bohr Institute (Faculty of SCIENCE PhD School) | C60: Denmark | D60: Capital Region | E60: Per position | F60: No central deadline: apply to advertised PhD positions on the UCPH job portal (each has its own deadline); applications go through the relevant department | G60: Not stated | I60: Not stated | J60: Not stated on the page checked | K60: Not stated | L60: Not stated | M60: Not stated | N60: Yes | O60: The faculty sets no English test: if English is not your principal language, you demonstrate it in an interview with your principal supervisor | P60: Required | Q60: You must have an agreement with a principal supervisor at the Faculty of Science before you apply for admission | R60: Guaranteed | S60: No unfunded admission: you need funding for salary and tuition fee to enrol (usually employment as a PhD fellow); UCPH stopped admitting self-paying PhD students in May 2025 | T60: Master's usually required | U60: Rules are from the Faculty of SCIENCE PhD School, which covers NBI (no separate NBI English admissions page was found). The PhD lasts three years after a master's. From 1 Jan 2027 UCPH charges a PhD tuition fee of DKK 85,000 per year for three years, which your funding must cover (phd.ku.dk enrolment page). Check each job ad for extra requirements. | V60: https://science.ku.dk/phd/appguide/ | W60: 2026-10-21
A61: Edinburgh | B61: University of Edinburgh · School of Physics and Astronomy | C61: United Kingdom | D61: Scotland | E61: 46409 | F61: Funding deadline: Physics Jan 22, 2027 (Astronomy/Astrophysics Jan 4, 2027). Admission without funding accepted until the end of June. | G61: Not stated | I61: Not stated | J61: Not stated on the page checked | K61: Not stated | L61: Not stated | M61: Not stated | N61: Conditional | O61: An English-taught degree counts only if your institution is on the University's approved list for non-majority-English-speaking countries | P61: Not required | Q61: No need to contact supervisors before applying unless you propose your own project; name preferred supervisors on the form | R61: Competitive | S61: School studentships include full tuition; UKRI limits how many international students can be funded, but other routes exist | T61: Direct from bachelor's | U61: Apply early if you need funding or a visa. | V61: https://www.ph.ed.ac.uk/studying/postgraduate-research/how-apply | W61: 2026-10-21
A62: University of Guelph | B62: University of Guelph · Department of Physics | C62: Canada | D62: Ontario | E62: 46419 | F62: Official pages disagree. Department page: February 1 for Fall (September) entry, with only domestic applicants considered after the deadline (Feb 1 also needed for award consideration). PhD program page: international Fall deadline May 1 (domestic August 31). Coded the earlier date; department recommends internationals apply 9+ months before the start term. Year inferred for Fall 2027. | G62: 125 | H62: CAD | I62: Not stated | J62: Not stated on the page checked | K62: Not stated | L62: Required | M62: 89 | N62: Conditional | O62: If your prior post-secondary study was taught in English you may request a waiver, decided case by case by the department; physics also asks for a test if your English-medium degree was completed more than two years ago | P62: Required | Q62: You do not need a supervisor before applying (list 2-3 potential supervisors), but approved applicants are admitted only if a supervisor match is found | R62: Typical | S62: Full funding typically provided to full-time thesis-based students without external funding (scholarships, TA, RA); no minimum amount stated | T62: Master's usually required | U62: Physics PhD run jointly with Waterloo through the Guelph-Waterloo Physics Institute (shared courses). Applications go through OUAC. | V62: https://www.uoguelph.ca/physics/future-students/grad-apply | W62: 2026-10-21
A63: UIUC | B63: University of Illinois Urbana-Champaign · Department of Physics | C63: USA | D63: Illinois | E63: 46402 | F63: January 15, 2027 for Fall 2027; all materials incl. letters and official scores by that date | G63: 90 | H63: USD | I63: Not stated | J63: No international fee-waiver route stated on the department pages checked | K63: Optional | L63: Optional | M63: Not stated | N63: No | O63: Exemption only for degrees/study in the U.S. or an approved English-primary country; India is not on the Graduate College's approved list | P63: Not stated | Q63: Admission is decided by the department committee; no pre-application supervisor requirement mentioned on the pages checked | R63: Typical | S63: Most admitted students are offered a Teaching Assistantship | T63: Direct from bachelor's | U63: Three letters of reference. Incomplete applications after January 15 are not considered. | V63: https://physics.illinois.edu/admissions/graduates/apply | W63: 2026-10-21
A64: University of Manitoba | B64: University of Manitoba · Department of Physics and Astronomy | C64: Canada | D64: Manitoba | E64: 46395 | F64: International applicants: January 8 for Fall (September) entry; applications reviewed on a rolling basis (Canadian/US: May 15). Taken from the Physics block of the program page's deadline widget; year inferred for Fall 2027. | G64: 130 | H64: CAD | I64: Not stated | J64: Not stated on the page checked | K64: Not stated | L64: Recommended | M64: 86 | N64: No | O64: Exemption only for degrees/diplomas from Canada or listed countries; India is not on the exemption list | P64: Required | Q64: Department cannot admit without a formal advisor commitment; contact a prospective advisor (via the associate head) before applying, and name your preferred supervisor in the application | R64: Guaranteed | S64: All students admitted to research-based graduate programs are guaranteed a department-set minimum stipend; 2026-27 PhD stipends CAD 27,000 (grant funded) to 40,000 (NSERC), excluding up to CAD 3,000 TA income | T64: Master's usually required | U64: Program listed as Physics and Astronomy (PhD); Medical and Health Physics PhD is a stream. Applying without prior advisor contact can forfeit the fee. All scholarships except NSERC are open to international students. | V64: https://umanitoba.ca/explore/programs-of-study/physics-phd | W64: 2026-10-21
A65: Maryland | B65: University of Maryland, College Park · Department of Physics | C65: USA | D65: Maryland | E65: 46367 | F65: December 11, 2026 for Fall 2027 (domestic and international) | G65: Not stated | I65: Not stated | J65: Not stated on the pages checked | K65: Not stated | L65: Optional | M65: Not stated | N65: Not stated | O65: Not stated on the page checked | P65: Not stated | Q65: No pre-application supervisor requirement mentioned | R65: Typical | S65: Virtually all PhD students have full support for the duration | T65: Not stated | U65: Three letters of recommendation; supplementary application required. Department site was unreachable (HTTP 502) on the check date. | V65: https://academiccatalog.umd.edu/graduate/programs/physics-phys/ | W65: 2026-10-21
A66: Minnesota | B66: University of Minnesota (Twin Cities) · School of Physics and Astronomy | C66: USA | D66: Minnesota | E66: 46371 | F66: December 15 for the following fall (window September-December). Year inferred. | G66: Not stated | I66: Not stated | J66: Not stated on the page checked | K66: Not considered | L66: Not considered | M66: 79 | N66: Not stated | O66: Exemption rules not shown on the page checked | P66: Not stated | Q66: No pre-application supervisor requirement mentioned | R66: Not stated | S66: Not stated on the page checked | T66: Not stated | U66: Department does not send acknowledgements or missing-item notices; check the portal yourself. | V66: https://cse.umn.edu/physics/graduate-admissions | W66: 2026-10-21
A67: University of Notre Dame | B67: University of Notre Dame · Department of Physics and Astronomy | C67: USA | D67: Indiana | E67: 46371 | F67: December 15 for full consideration (year inferred); primarily fall entry | G67: 75 | H67: USD | I67: Available | J67: Graduate School waivers for need/financial hardship (bank or mobile-money statement accepted), veterans, national-fellowship applicants, or at department discretion; no citizenship limit stated. Physics also offers a limited number of departmental waivers. | K67: Not considered | L67: Not considered | M67: 80 | N67: Yes | O67: Waived for anyone with a bachelor's (or higher) degree, or at least two years of post-secondary study, at an English-medium institution | P67: Not required | Q67: Students are not admitted to a specific advisor, though funded advisors' recommendations weigh strongly; must state experiment vs theory preference | R67: Guaranteed | S67: All admitted students receive full tuition support and a stipend (TA first, RA later) | T67: Direct from bachelor's | U67: Selected applicants get an online interview. Admission decision cannot be made until TOEFL/IELTS scores arrive. Strong applicants automatically considered for internal fellowships. | V67: https://physics.nd.edu/graduate/apply/ | W67: 2026-10-21
A68: Ottawa | B68: University of Ottawa (Ottawa-Carleton Institute for Physics) · Department of Physics | C68: Canada | D68: Ontario | E68: Not stated | F68: Physics-specific deadline not shown on the catalogue page checked | G68: Not stated | I68: Not stated | J68: Not stated on the page checked | K68: Not stated | L68: Not stated | M68: Not stated | N68: Not stated | O68: Exemption rules not shown on the page checked | P68: Required | Q68: Supervisor's name required AT APPLICATION; you must be accepted by a thesis supervisor to register | R68: Not stated | S68: International students must show financial support (supervisor stipend plus awards/trust funds) | T68: Master's usually required | U68: Joint uOttawa-Carleton institute; your supervisor's home university awards the degree. | V68: https://catalogue.uottawa.ca/en/graduate/doctorate-philosophy-physics/ | W68: 2026-10-21
A69: Padova | B69: University of Padova (Università degli Studi di Padova) · PhD Course in Physics | C69: Italy | D69: Veneto (Padua) | E69: Not stated | F69: Annual call (bando). The 2026/27 (42nd cycle) call closed May 20, 2026, 1 pm (2025/26: May 13, 2025); a smaller summer call for extra places closed Aug 26, 2026. The 2027/28 (43rd cycle) call is not yet published. | G69: Not stated | I69: Not stated | J69: Not stated on the page checked | K69: Not stated | L69: Not stated | M69: Not stated | N69: Not stated | O69: Not stated on the page checked | P69: Not stated | Q69: Admission is by public competition (admission exam set out in each course information sheet); no prior supervisor agreement mentioned on the pages checked | R69: Competitive | S69: Each course lists its number of places and scholarships; some places are awarded without a scholarship. Physics figures are only in the PDF information sheet. | T69: Master's usually required | U69: Apply on pica.cineca.it. The Physics information sheet (places, scholarships, exam format) is a PDF and was not checked. The course website (phd.fisica.unipd.it) and department site could not be fetched. 531 PhD positions university-wide for 2026/27. | V69: https://www.unipd.it/en/dottorato/dottorati-42-ciclo | W69: 2026-10-21
A70: University of Pittsburgh | B70: University of Pittsburgh · Department of Physics and Astronomy | C70: USA | D70: Pennsylvania | E70: 46371 | F70: December 15, 2026 for Fall 2027 (application opens September 8, 2026); Fall entry only | G70: 75 | H70: USD | I70: Available | J70: Dietrich School fee waivers via survey, case-by-case; all applicants encouraged to apply (international section says "All of the above plus"); requests submitted by Dec 20 still get full consideration | K70: Optional | L70: Optional | M70: 90 | N70: Not stated | O70: Exceptions case-by-case for a U.S. bachelor's or nationals of countries on a PDF list (not checked); no rule for English-medium Indian degrees on the pages checked | P70: Not required | Q70: No need to identify a faculty member, though mentioning interested faculty helps | R70: Guaranteed | S70: PhD students in good standing guaranteed 5 years of support (TA, research, etc.); MS students self-funded | T70: Direct from bachelor's | U70: Separate Astrophysics PhD in the same department. Admitted students with TOEFL below 100 take an English test at orientation. GPA 3.0 needed for a TA award. | V70: https://www.physicsandastronomy.pitt.edu/graduate/how-apply | W70: 2026-10-21
A71: University of Saskatchewan | B71: University of Saskatchewan · Department of Physics and Engineering Physics | C71: Canada | D71: Saskatchewan | E71: Rolling | F71: No fixed deadline; applications accepted throughout the year | G71: 145 | H71: CAD | I71: Not stated | J71: Not stated on the page checked | K71: Not stated | L71: Not stated | M71: 86 | N71: Conditional | O71: Exempt after 3+ consecutive years of full-time study (or a graduate degree) at an institution whose exclusive language of instruction is English (eligible-institution list); acceptance is at the department's discretion and a test can still be required | P71: Recommended | Q71: Supervisor approval recommended before applying; applications without a confirmed supervisor are circulated to faculty | R71: Guaranteed | S71: PhD students guaranteed a minimum stipend of CAD 20,000/year for 4 years, contingent on meeting standard academic requirements | T71: Master's usually required | U71: PhD tuition is the same for international and domestic students (CAD 5,637/year in 2026-27). Degrees awarded in Physics or Engineering Physics. | V71: https://grad.usask.ca/programs/physics-engineering-physics.php | W71: 2026-10-21
A72: UT Austin | B72: University of Texas at Austin · Department of Physics | C72: USA | D72: Texas | E72: 46357 | F72: 1 December, 11:59 p.m. CST for Fall admission (one-week grace period stated). Year inferred for Fall 2027. | G72: 90 | H72: USD | I72: Limited | J72: Graduate School waivers for applicants meeting certain criteria; department not involved. Check criteria for international eligibility. | K72: Not considered | L72: Optional | M72: 79 | N72: Yes | O72: India is on UT's list of qualifying countries exempt from TOEFL/IELTS (also exempt with a bachelor's from a U.S./qualifying-country institution) | P72: Not stated | Q72: Admission is decided by the department committee; no pre-application supervisor requirement mentioned on the pages checked | R72: Not stated | S72: PhD funding terms not stated on the admissions page (master's applicants get no support) | T72: Direct from bachelor's | U72: Review begins mid-January; international decisions typically early to mid-March. | V72: https://physics.utexas.edu/academics/admissions | W72: 2026-10-21
A73: Toronto | B73: University of Toronto · Department of Physics | C73: Canada | D73: Ontario | E73: 46367 | F73: December 11, 11:59pm, all materials including both reference letters. Year inferred for September 2027 entry. | G73: 135 | H73: CAD | I73: None | J73: Fee cannot be waived under any circumstances | K73: Not required | L73: Not required | M73: 93 | N73: Yes | O73: No test if your degree is from a university where instruction AND examination are in English; an official letter is needed unless the transcript says so | P73: Not required | Q73: No supervisor needed to apply; MSc and 5-year direct-entry PhD students pick one after arrival; 4-year PhD entrants (with a master's) must secure one before registration, typically by May | R73: Not stated | S73: Funding package not described on the admissions pages checked | T73: Either | U73: Exactly two reference letters (no more). January start is domestic-only. | V73: https://www.physics.utoronto.ca/graduate/prospective-students/graduate-admissions-department-physics/application-procedure/ | W73: 2026-10-21
A74: University of Virginia | B74: University of Virginia · Department of Physics (Graduate School of Arts and Sciences) | C74: USA | D74: Virginia | E74: 46371 | F74: PhD Physics: December 15 (year inferred; portal opens October 1). Physics MS has a separate Jan 15 / rolling-to-May 1 schedule. | G74: 85 | H74: USD | I74: Limited | J74: Waivers for US citizens/PRs with hardship; internationals only if citizens of UN least developed countries (India is not on the list); GSAS gives no waiver codes | K74: Not required | L74: Required | M74: 90 | N74: Conditional | O74: Automatic waiver if the whole undergraduate degree is from an institution where English is the primary language of instruction, with evidence (transcript or primary-language certificate); other proof considered case by case | P74: Not stated | Q74: Not stated on the page checked | R74: Guaranteed | S74: Doctoral admits get at least five years of support: 12-month stipend $37,260, full tuition/fees remission, single health insurance | T74: Not stated | U74: Physics department site (physics.virginia.edu) could not be fetched (connection reset); all facts are from Graduate School of Arts and Sciences pages. Enrolling students without an English-medium undergraduate degree must take the UVELPE exam in May. Id "uva" is used by University of Amsterdam. | V74: https://graduate.as.virginia.edu/requirements | W74: 2026-10-22
A75: University of Washington (Seattle) | B75: University of Washington (Seattle) · Department of Physics | C75: USA | D75: Washington | E75: 46371 | F75: December 15, 2026 (autumn quarter entry only) | G75: 90 | H75: USD | I75: Domestic only | J75: Physics gives no waivers; Graduate School need-based and prep-program waivers are for U.S. citizens, permanent residents and undocumented applicants | K75: Not stated | L75: Optional | M75: 80 | N75: Conditional | O75: An English-medium degree counts, but Indian applicants need official documentation from the institution that all instruction was in English (India is not on the no-documentation country list) and must have been in residence on or near the campus for the whole degree (no remote/online study) | P75: Not required | Q75: Admission is to the department PhD program, not to a research group; students find a research advisor during the first years | R75: Typical | S75: Department aims to support all full-time PhD students making satisfactory progress; most first-years get full TA support in the offer; later support via RA/TA (student must find an advisor for RA) | T75: Direct from bachelor's | U75: TA appointments for non-native speakers fall under UW Graduate School Policy 5.2. Students scoring below the recommended English score must take Academic English Program courses (extra fees). | V75: https://phys.washington.edu/graduate-programs | W75: 2026-10-21
A76: Waterloo | B76: University of Waterloo · Physics and Astronomy | C76: Canada | D76: Ontario | E76: 46396 | F76: January 9 for September admission (early applications encouraged). Year inferred for September 2027 entry. | G76: 150 | H76: CAD | I76: Not stated | J76: No fee-waiver route stated on the pages checked | K76: Not stated | L76: Recommended | M76: 90 | N76: Conditional | O76: Exempt only if 3+ years of study at a university listed in WHED with English as the ONLY language of instruction; exemption expires 2 years after graduation; medium-of-instruction letters are not accepted | P76: Required | Q76: Admission requires a faculty member willing to supervise you; contact before or after applying and name supervisors on the application | R76: Guaranteed | S76: Funding package for all graduate students within program time limits (GRS, TA, awards); TA two of three terms | T76: Master's usually required | U76: Physics PhD streams include Nanotechnology and Quantum Information (IQC, Perimeter affiliations). | V76: https://uwaterloo.ca/physics-astronomy/graduate-studies/how-apply | W76: 2026-10-21
A77: UW-Madison | B77: University of Wisconsin-Madison · Department of Physics | C77: USA | D77: Wisconsin | E77: 46371 | F77: December 15, 2026 for Fall 2027 (all materials via the Graduate School application) | G77: Not stated | I77: Domestic only | J77: Department gives no waivers; Graduate School fee grants are for U.S. citizens and permanent residents only | K77: Not considered | L77: Optional | M77: 92 | N77: Check tool | O77: Graduate School decides via a country-selector tool; result for India not shown in static page text | P77: Not required | Q77: Advisor chosen after entry; early selection encouraged; any physics faculty or affiliate | R77: Guaranteed | S77: Five years of financial support guaranteed for admitted PhD students | T77: Direct from bachelor's | U77: Official GRE/TOEFL scores must come directly from ETS. Segregated fees about $800/semester for full-time students. | V77: https://www.physics.wisc.edu/graduate/phd-program/ | W77: 2026-10-21
A78: Zurich (UZH) | B78: University of Zurich (UZH) · Doctoral Program in Physics (Physics Institute) | C78: Switzerland | D78: Zurich | E78: Per position | F78: No central call: apply to advertised open positions or contact group leaders directly. After a group accepts you, the UZH Admissions Office window for Fall-semester doctoral studies is 1 January to 31 July (pre-application required) | G78: 100 | H78: CHF | I78: Not stated | J78: Not stated on the page checked | K78: Not stated | L78: Not stated | M78: Not stated | N78: Not stated | O78: No English-test rule stated on the pages checked (the department only says good German and/or English is essential) | P78: Required | Q78: A group leader must accept you and sign a Confirmation of Supervision; the Admissions Office cannot admit you without it | R78: Typical | S78: PhD students are normally salaried; the department says the salary covers local living costs including social and health insurance | T78: Master's usually required | U78: Faculty of Science (MNF). 12 ECTS of coursework; PhD usually takes 3–4 years. Non-EU/EFTA citizens need a visa and work permit (UZH generally applies on your behalf), and processing can take up to three months. | V78: https://www.physik.uzh.ch/en/study/Study-Degree-Programmes/phd.html | W78: 2026-10-21
A79: Paris-Saclay | B79: Université Paris-Saclay · PhD Program Physics – Graduate School Physics (doctoral schools EDOM, PHENIICS, AAIF, EDPIF) | C79: France | D79: Île-de-France (Saclay/Orsay) | E79: Not stated | F79: Only the 2024 calendar is shown: ADUM applications closed Apr 23 (EDOM), Apr 29 (EDPIF) and May 10, 2024 (PHENIICS), with auditions late May to early June. 2027 dates are not published on the page checked. | G79: Not stated | I79: Not stated | J79: Not stated on the page checked | K79: Not stated | L79: Not stated | M79: Not stated | N79: Not stated | O79: No English-test rule stated; EDPIF auditions may be given in English or French | P79: Required | Q79: You need a thesis topic and the thesis director's agreement before applying; the director and lab head must give favourable opinions on ADUM | R79: Guaranteed | S79: Students admitted to the programme get a 3-year salaried public doctoral contract. Contracts are limited and awarded by each doctoral school's competition (file review + audition); every PhD application must include funding or proof of financial means. | T79: Master's usually required | U79: Find a topic (ADUM thesis offers), then apply on ADUM to the doctoral school of that topic. Each school examines the file, then holds a short audition (about 15 to 25 minutes depending on the school; EDOM allows videoconference). The page's calendar is for 2024, so check each doctoral school for the 2027 campaign. | V79: https://www.universite-paris-saclay.fr/en/phd-program-physics-graduate-school-physics | W79: 2026-10-21
A80: Uppsala | B80: Uppsala University · Department of Physics and Astronomy | C80: Sweden | D80: Uppsala | E80: Per position | F80: No common call or admission date: departments advertise positions continuously during the year, each open for at least three weeks before its deadline | G80: 0 | I80: No fee | J80: No fee to waive | K80: Not stated | L80: Not stated | M80: Not stated | N80: Not stated | O80: Not stated on the pages checked | P80: Required | Q80: Admission is decided after consultation with the supervisors, who normally set the main structure of the research project at admission | R80: Guaranteed | S80: On admission the department commits to four years of full-time funding, normally as an employed doctoral student. Scholarships are used restrictively and must be topped up to the employed-student level | T80: Master's usually required | U80: Physics and Theoretical Physics have separate general syllabuses under the Faculty of Science and Technology. The university PhD page requires 'good English language skills' but gives no test minimum, so check each advertisement. The funding rules come from a Faculty staff page. | V80: https://www.uu.se/en/department/physics-and-astronomy/study/phd-studies | W80: 2026-10-21
A81: Vanderbilt University | B81: Vanderbilt University · Department of Physics and Astronomy | C81: USA | D81: Tennessee | E81: 46357 | F81: December 1, 2026 for Fall 2027 (applications open August 1, 2026) | G81: 95 | H81: USD | I81: Limited | J81: Internationals only eligible for a discretionary department waiver; Physics grants a small number (rolling from late October), requested by email after submitting and before the deadline | K81: Not considered | L81: Not considered | M81: 89 | N81: Conditional | O81: Waived if the entire bachelor's was taught in English in a country with multiple official languages including English (India's case), with proof: Registrar/Controller of Examinations MOI letter, or transcript/mark sheet stating English medium. Graduate School summary also lists India among English-language university countries. | P81: Not stated | Q81: Not stated on the page checked | R81: Guaranteed | S81: Students receive a five-year support package: full tuition waiver, health insurance, stipend (currently $36,500/yr) | T81: Not stated | U81: Separate Astrophysics PhD in the same department. Statement of purpose 1000-2000 words. Funded campus visit only for admits residing in the USA. | V81: https://as.vanderbilt.edu/physics-astronomy/phd-physics-admissions/ | W81: 2026-10-21
A82: Western University | B82: Western University · Department of Physics and Astronomy | C82: Canada | D82: Ontario | E82: 46447 | F82: International applicants: March 1, 2027, including reference letters and transcripts. Applications are reviewed first-come, first-served with rolling offers, so applying early helps. (Domestic: up to August 30/31.) | G82: 185 | H82: CAD | I82: Not stated | J82: Not stated on the page checked | K82: Not required | L82: Recommended | M82: 90 | N82: No | O82: Automatic exemption only if English is your first language, or after 2+ full-time years at an English-speaking institution in a listed country whose primary language is English. India is not on the list. | P82: Required | Q82: Every admission offer is made together with the student's faculty supervisor; contacting potential supervisors before applying is strongly encouraged | R82: Guaranteed | S82: All MSc and PhD students receive a funding package covering living expenses and tuition (scholarship, fellowship and TA); no minimum amount is stated on the page (2026-27 stipend examples are in a linked PDF) | T82: Master's usually required | U82: Exemption country list (SGPS) does not include India. Application fee is refunded to admitted students who enrol in Physics & Astronomy. Department TOEFL/IELTS minimums exceed SGPS minimums. | V82: https://www.physics.uwo.ca/graduate/future_students/admission_requirements.html | W82: 2026-10-21
A83: Yale University | B83: Yale University · Department of Physics | C83: USA | D83: Connecticut | E83: 46371 | F83: December 15, 2026, 11:59 pm Eastern (GSAS lists Physics under Dec 15, 2026) | G83: 105 | H83: USD | I83: Available | J83: Non-US citizens are eligible to request; granted for listed special programs or documented financial hardship. Request separately, well before the Dec 15 deadline (form closes Jan 2). | K83: Optional | L83: Optional | M83: Not stated | N83: Conditional | O83: Exempt with a bachelor's from an institution where English is the primary language of instruction AND at least three years in residence there; answered in the application, no separate documents; a master's or PhD does not count | P83: Not stated | Q83: No pre-application supervisor requirement mentioned | R83: Guaranteed | S83: Every PhD student gets full tuition plus a stipend for at least five years; department FAQ says all admitted students receive financial aid | T83: Direct from bachelor's | U83: Applied Physics and Astronomy are separate Yale programs (also Dec 15). The department apply page still shows an old 'deadline has passed' banner above the current Dec 15, 2026 text. | V83: https://physics.yale.edu/apply | W83: 2026-10-21

Sheet Shortlist
A1: Program (choose) | B1: Country | C1: Deadline | D1: Days left | E1: Fee | F1: Currency | G1: Intl fee waiver | H1: Physics GRE | I1: English waiver | J1: Supervisor | K1: Status | L1: SOP ready | M1: Letters confirmed | N1: Fee paid / waiver | O1: My notes
B2: =IF($A2="","",INDEX(Programs!$C$2:$C$83,MATCH($A2,Programs!$A$2:$A$83,0))) | C2: =IF($A2="","",INDEX(Programs!$E$2:$E$83,MATCH($A2,Programs!$A$2:$A$83,0))) | D2: =IF(ISNUMBER(C2),C2-TODAY(),"") | E2: =IF($A2="","",INDEX(Programs!$G$2:$G$83,MATCH($A2,Programs!$A$2:$A$83,0))) | F2: =IF($A2="","",INDEX(Programs!$H$2:$H$83,MATCH($A2,Programs!$A$2:$A$83,0))) | G2: =IF($A2="","",INDEX(Programs!$I$2:$I$83,MATCH($A2,Programs!$A$2:$A$83,0))) | H2: =IF($A2="","",INDEX(Programs!$L$2:$L$83,MATCH($A2,Programs!$A$2:$A$83,0))) | I2: =IF($A2="","",INDEX(Programs!$N$2:$N$83,MATCH($A2,Programs!$A$2:$A$83,0))) | J2: =IF($A2="","",INDEX(Programs!$P$2:$P$83,MATCH($A2,Programs!$A$2:$A$83,0)))
B3: =IF($A3="","",INDEX(Programs!$C$2:$C$83,MATCH($A3,Programs!$A$2:$A$83,0))) | C3: =IF($A3="","",INDEX(Programs!$E$2:$E$83,MATCH($A3,Programs!$A$2:$A$83,0))) | D3: =IF(ISNUMBER(C3),C3-TODAY(),"") | E3: =IF($A3="","",INDEX(Programs!$G$2:$G$83,MATCH($A3,Programs!$A$2:$A$83,0))) | F3: =IF($A3="","",INDEX(Programs!$H$2:$H$83,MATCH($A3,Programs!$A$2:$A$83,0))) | G3: =IF($A3="","",INDEX(Programs!$I$2:$I$83,MATCH($A3,Programs!$A$2:$A$83,0))) | H3: =IF($A3="","",INDEX(Programs!$L$2:$L$83,MATCH($A3,Programs!$A$2:$A$83,0))) | I3: =IF($A3="","",INDEX(Programs!$N$2:$N$83,MATCH($A3,Programs!$A$2:$A$83,0))) | J3: =IF($A3="","",INDEX(Programs!$P$2:$P$83,MATCH($A3,Programs!$A$2:$A$83,0)))
B4: =IF($A4="","",INDEX(Programs!$C$2:$C$83,MATCH($A4,Programs!$A$2:$A$83,0))) | C4: =IF($A4="","",INDEX(Programs!$E$2:$E$83,MATCH($A4,Programs!$A$2:$A$83,0))) | D4: =IF(ISNUMBER(C4),C4-TODAY(),"") | E4: =IF($A4="","",INDEX(Programs!$G$2:$G$83,MATCH($A4,Programs!$A$2:$A$83,0))) | F4: =IF($A4="","",INDEX(Programs!$H$2:$H$83,MATCH($A4,Programs!$A$2:$A$83,0))) | G4: =IF($A4="","",INDEX(Programs!$I$2:$I$83,MATCH($A4,Programs!$A$2:$A$83,0))) | H4: =IF($A4="","",INDEX(Programs!$L$2:$L$83,MATCH($A4,Programs!$A$2:$A$83,0))) | I4: =IF($A4="","",INDEX(Programs!$N$2:$N$83,MATCH($A4,Programs!$A$2:$A$83,0))) | J4: =IF($A4="","",INDEX(Programs!$P$2:$P$83,MATCH($A4,Programs!$A$2:$A$83,0)))
B5: =IF($A5="","",INDEX(Programs!$C$2:$C$83,MATCH($A5,Programs!$A$2:$A$83,0))) | C5: =IF($A5="","",INDEX(Programs!$E$2:$E$83,MATCH($A5,Programs!$A$2:$A$83,0))) | D5: =IF(ISNUMBER(C5),C5-TODAY(),"") | E5: =IF($A5="","",INDEX(Programs!$G$2:$G$83,MATCH($A5,Programs!$A$2:$A$83,0))) | F5: =IF($A5="","",INDEX(Programs!$H$2:$H$83,MATCH($A5,Programs!$A$2:$A$83,0))) | G5: =IF($A5="","",INDEX(Programs!$I$2:$I$83,MATCH($A5,Programs!$A$2:$A$83,0))) | H5: =IF($A5="","",INDEX(Programs!$L$2:$L$83,MATCH($A5,Programs!$A$2:$A$83,0))) | I5: =IF($A5="","",INDEX(Programs!$N$2:$N$83,MATCH($A5,Programs!$A$2:$A$83,0))) | J5: =IF($A5="","",INDEX(Programs!$P$2:$P$83,MATCH($A5,Programs!$A$2:$A$83,0)))
B6: =IF($A6="","",INDEX(Programs!$C$2:$C$83,MATCH($A6,Programs!$A$2:$A$83,0))) | C6: =IF($A6="","",INDEX(Programs!$E$2:$E$83,MATCH($A6,Programs!$A$2:$A$83,0))) | D6: =IF(ISNUMBER(C6),C6-TODAY(),"") | E6: =IF($A6="","",INDEX(Programs!$G$2:$G$83,MATCH($A6,Programs!$A$2:$A$83,0))) | F6: =IF($A6="","",INDEX(Programs!$H$2:$H$83,MATCH($A6,Programs!$A$2:$A$83,0))) | G6: =IF($A6="","",INDEX(Programs!$I$2:$I$83,MATCH($A6,Programs!$A$2:$A$83,0))) | H6: =IF($A6="","",INDEX(Programs!$L$2:$L$83,MATCH($A6,Programs!$A$2:$A$83,0))) | I6: =IF($A6="","",INDEX(Programs!$N$2:$N$83,MATCH($A6,Programs!$A$2:$A$83,0))) | J6: =IF($A6="","",INDEX(Programs!$P$2:$P$83,MATCH($A6,Programs!$A$2:$A$83,0)))
B7: =IF($A7="","",INDEX(Programs!$C$2:$C$83,MATCH($A7,Programs!$A$2:$A$83,0))) | C7: =IF($A7="","",INDEX(Programs!$E$2:$E$83,MATCH($A7,Programs!$A$2:$A$83,0))) | D7: =IF(ISNUMBER(C7),C7-TODAY(),"") | E7: =IF($A7="","",INDEX(Programs!$G$2:$G$83,MATCH($A7,Programs!$A$2:$A$83,0))) | F7: =IF($A7="","",INDEX(Programs!$H$2:$H$83,MATCH($A7,Programs!$A$2:$A$83,0))) | G7: =IF($A7="","",INDEX(Programs!$I$2:$I$83,MATCH($A7,Programs!$A$2:$A$83,0))) | H7: =IF($A7="","",INDEX(Programs!$L$2:$L$83,MATCH($A7,Programs!$A$2:$A$83,0))) | I7: =IF($A7="","",INDEX(Programs!$N$2:$N$83,MATCH($A7,Programs!$A$2:$A$83,0))) | J7: =IF($A7="","",INDEX(Programs!$P$2:$P$83,MATCH($A7,Programs!$A$2:$A$83,0)))
B8: =IF($A8="","",INDEX(Programs!$C$2:$C$83,MATCH($A8,Programs!$A$2:$A$83,0))) | C8: =IF($A8="","",INDEX(Programs!$E$2:$E$83,MATCH($A8,Programs!$A$2:$A$83,0))) | D8: =IF(ISNUMBER(C8),C8-TODAY(),"") | E8: =IF($A8="","",INDEX(Programs!$G$2:$G$83,MATCH($A8,Programs!$A$2:$A$83,0))) | F8: =IF($A8="","",INDEX(Programs!$H$2:$H$83,MATCH($A8,Programs!$A$2:$A$83,0))) | G8: =IF($A8="","",INDEX(Programs!$I$2:$I$83,MATCH($A8,Programs!$A$2:$A$83,0))) | H8: =IF($A8="","",INDEX(Programs!$L$2:$L$83,MATCH($A8,Programs!$A$2:$A$83,0))) | I8: =IF($A8="","",INDEX(Programs!$N$2:$N$83,MATCH($A8,Programs!$A$2:$A$83,0))) | J8: =IF($A8="","",INDEX(Programs!$P$2:$P$83,MATCH($A8,Programs!$A$2:$A$83,0)))
B9: =IF($A9="","",INDEX(Programs!$C$2:$C$83,MATCH($A9,Programs!$A$2:$A$83,0))) | C9: =IF($A9="","",INDEX(Programs!$E$2:$E$83,MATCH($A9,Programs!$A$2:$A$83,0))) | D9: =IF(ISNUMBER(C9),C9-TODAY(),"") | E9: =IF($A9="","",INDEX(Programs!$G$2:$G$83,MATCH($A9,Programs!$A$2:$A$83,0))) | F9: =IF($A9="","",INDEX(Programs!$H$2:$H$83,MATCH($A9,Programs!$A$2:$A$83,0))) | G9: =IF($A9="","",INDEX(Programs!$I$2:$I$83,MATCH($A9,Programs!$A$2:$A$83,0))) | H9: =IF($A9="","",INDEX(Programs!$L$2:$L$83,MATCH($A9,Programs!$A$2:$A$83,0))) | I9: =IF($A9="","",INDEX(Programs!$N$2:$N$83,MATCH($A9,Programs!$A$2:$A$83,0))) | J9: =IF($A9="","",INDEX(Programs!$P$2:$P$83,MATCH($A9,Programs!$A$2:$A$83,0)))
B10: =IF($A10="","",INDEX(Programs!$C$2:$C$83,MATCH($A10,Programs!$A$2:$A$83,0))) | C10: =IF($A10="","",INDEX(Programs!$E$2:$E$83,MATCH($A10,Programs!$A$2:$A$83,0))) | D10: =IF(ISNUMBER(C10),C10-TODAY(),"") | E10: =IF($A10="","",INDEX(Programs!$G$2:$G$83,MATCH($A10,Programs!$A$2:$A$83,0))) | F10: =IF($A10="","",INDEX(Programs!$H$2:$H$83,MATCH($A10,Programs!$A$2:$A$83,0))) | G10: =IF($A10="","",INDEX(Programs!$I$2:$I$83,MATCH($A10,Programs!$A$2:$A$83,0))) | H10: =IF($A10="","",INDEX(Programs!$L$2:$L$83,MATCH($A10,Programs!$A$2:$A$83,0))) | I10: =IF($A10="","",INDEX(Programs!$N$2:$N$83,MATCH($A10,Programs!$A$2:$A$83,0))) | J10: =IF($A10="","",INDEX(Programs!$P$2:$P$83,MATCH($A10,Programs!$A$2:$A$83,0)))
B11: =IF($A11="","",INDEX(Programs!$C$2:$C$83,MATCH($A11,Programs!$A$2:$A$83,0))) | C11: =IF($A11="","",INDEX(Programs!$E$2:$E$83,MATCH($A11,Programs!$A$2:$A$83,0))) | D11: =IF(ISNUMBER(C11),C11-TODAY(),"") | E11: =IF($A11="","",INDEX(Programs!$G$2:$G$83,MATCH($A11,Programs!$A$2:$A$83,0))) | F11: =IF($A11="","",INDEX(Programs!$H$2:$H$83,MATCH($A11,Programs!$A$2:$A$83,0))) | G11: =IF($A11="","",INDEX(Programs!$I$2:$I$83,MATCH($A11,Programs!$A$2:$A$83,0))) | H11: =IF($A11="","",INDEX(Programs!$L$2:$L$83,MATCH($A11,Programs!$A$2:$A$83,0))) | I11: =IF($A11="","",INDEX(Programs!$N$2:$N$83,MATCH($A11,Programs!$A$2:$A$83,0))) | J11: =IF($A11="","",INDEX(Programs!$P$2:$P$83,MATCH($A11,Programs!$A$2:$A$83,0)))
B12: =IF($A12="","",INDEX(Programs!$C$2:$C$83,MATCH($A12,Programs!$A$2:$A$83,0))) | C12: =IF($A12="","",INDEX(Programs!$E$2:$E$83,MATCH($A12,Programs!$A$2:$A$83,0))) | D12: =IF(ISNUMBER(C12),C12-TODAY(),"") | E12: =IF($A12="","",INDEX(Programs!$G$2:$G$83,MATCH($A12,Programs!$A$2:$A$83,0))) | F12: =IF($A12="","",INDEX(Programs!$H$2:$H$83,MATCH($A12,Programs!$A$2:$A$83,0))) | G12: =IF($A12="","",INDEX(Programs!$I$2:$I$83,MATCH($A12,Programs!$A$2:$A$83,0))) | H12: =IF($A12="","",INDEX(Programs!$L$2:$L$83,MATCH($A12,Programs!$A$2:$A$83,0))) | I12: =IF($A12="","",INDEX(Programs!$N$2:$N$83,MATCH($A12,Programs!$A$2:$A$83,0))) | J12: =IF($A12="","",INDEX(Programs!$P$2:$P$83,MATCH($A12,Programs!$A$2:$A$83,0)))
B13: =IF($A13="","",INDEX(Programs!$C$2:$C$83,MATCH($A13,Programs!$A$2:$A$83,0))) | C13: =IF($A13="","",INDEX(Programs!$E$2:$E$83,MATCH($A13,Programs!$A$2:$A$83,0))) | D13: =IF(ISNUMBER(C13),C13-TODAY(),"") | E13: =IF($A13="","",INDEX(Programs!$G$2:$G$83,MATCH($A13,Programs!$A$2:$A$83,0))) | F13: =IF($A13="","",INDEX(Programs!$H$2:$H$83,MATCH($A13,Programs!$A$2:$A$83,0))) | G13: =IF($A13="","",INDEX(Programs!$I$2:$I$83,MATCH($A13,Programs!$A$2:$A$83,0))) | H13: =IF($A13="","",INDEX(Programs!$L$2:$L$83,MATCH($A13,Programs!$A$2:$A$83,0))) | I13: =IF($A13="","",INDEX(Programs!$N$2:$N$83,MATCH($A13,Programs!$A$2:$A$83,0))) | J13: =IF($A13="","",INDEX(Programs!$P$2:$P$83,MATCH($A13,Programs!$A$2:$A$83,0)))
... B31: =IF($A31="","",INDEX(Programs!$C$2:$C$83,MATCH($A31,Programs!$A$2:$A$83,0))) | C31: =IF($A31="","",INDEX(Programs!$E$2:$E$83,MATCH($A31,Programs!$A$2:$A$83,0))) | D31: =IF(ISNUMBER(C31),C31-TODAY(),"") | E31: =IF($A31="","",INDEX(Programs!$G$2:$G$83,MATCH($A31,Programs!$A$2:$A$83,0))) | F31: =IF($A31="","",INDEX(Programs!$H$2:$H$83,MATCH($A31,Programs!$A$2:$A$83,0))) | G31: =IF($A31="","",INDEX(Programs!$I$2:$I$83,MATCH($A31,Programs!$A$2:$A$83,0))) | H31: =IF($A31="","",INDEX(Programs!$L$2:$L$83,MATCH($A31,Programs!$A$2:$A$83,0))) | I31: =IF($A31="","",INDEX(Programs!$N$2:$N$83,MATCH($A31,Programs!$A$2:$A$83,0))) | J31: =IF($A31="","",INDEX(Programs!$P$2:$P$83,MATCH($A31,Programs!$A$2:$A$83,0)))

Sheet Budget
A1: Item | B1: USD | C1: CAD | D1: GBP | E1: EUR | F1: CHF | G1: Notes
A2: Application fees on your shortlist (excludes rows marked Waived) | B2: =SUMIFS(Shortlist!$E$2:$E$31,Shortlist!$F$2:$F$31,"USD",Shortlist!$N$2:$N$31,"<>Waived") | C2: =SUMIFS(Shortlist!$E$2:$E$31,Shortlist!$F$2:$F$31,"CAD",Shortlist!$N$2:$N$31,"<>Waived") | D2: =SUMIFS(Shortlist!$E$2:$E$31,Shortlist!$F$2:$F$31,"GBP",Shortlist!$N$2:$N$31,"<>Waived") | E2: =SUMIFS(Shortlist!$E$2:$E$31,Shortlist!$F$2:$F$31,"EUR",Shortlist!$N$2:$N$31,"<>Waived") | F2: =SUMIFS(Shortlist!$E$2:$E$31,Shortlist!$F$2:$F$31,"CHF",Shortlist!$N$2:$N$31,"<>Waived") | G2: Calculated
A3: English test (booking + extra score reports) | G3: Enter from the official test website
A4: GRE / Physics GRE (booking + score reports) | G4: Enter only if a program on your list needs it
A5: Transcripts, credential evaluation, courier | G5: Enter from your university / evaluator
A6: Other
A7: Total | B7: =SUM(B2:B6) | C7: =SUM(C2:C6) | D7: =SUM(D2:D6) | E7: =SUM(E2:E6) | F7: =SUM(F2:F6)
A9: Rupees per 1 unit (Bank of Canada, 2026-10-21): edit to today's rate, or your own currency | B9: 94.47 | C9: 67.2 | D9: 126.52 | E9: 106.08 | F9: 114.56 | G9: Pre-filled; banks and cards add a margin
A10: Total in rupees (approximate) | B10: =IF(B9="",0,B7*B9)+IF(C9="",0,C7*C9)+IF(D9="",0,D7*D9)+IF(E9="",0,E7*E9)+IF(F9="",0,F7*F9) | G10: Currencies without a rate are left out

Sheet Recommenders
A1: Recommender | B1: Email | C1: Relationship | D1: Asked on | E1: Packet sent | F1: Programs invited | G1: Status | H1: Follow up by
H2: =IF(D2="","",D2+14)
H3: =IF(D3="","",D3+14)
H4: =IF(D4="","",D4+14)
H5: =IF(D5="","",D5+14)
H6: =IF(D6="","",D6+14)
H7: =IF(D7="","",D7+14)
H8: =IF(D8="","",D8+14)

Sheet Supervisor outreach
A1: Professor | B1: University | C1: Group / topic | D1: Paper you read | E1: Emailed on | F1: Follow up on | G1: Reply | H1: Next step
F2: =IF(E2="","",E2+10)
F3: =IF(E3="","",E3+10)
F4: =IF(E4="","",E4+10)
F5: =IF(E5="","",E5+10)
F6: =IF(E6="","",E6+10)
F7: =IF(E7="","",E7+10)
F8: =IF(E8="","",E8+10)
F9: =IF(E9="","",E9+10)
F10: =IF(E10="","",E10+10)
F11: =IF(E11="","",E11+10)
F12: =IF(E12="","",E12+10)
F13: =IF(E13="","",E13+10)
... F30: =IF(E30="","",E30+10)

Sheet Sources
A1: Program | B1: Field | C1: Code | D1: Value | E1: Official quote | F1: Source URL | G1: Flags | H1: Checked
A2: Aalto University | B2: Deadline (2027 entry) | C2: Rolling | D2: Continuous admission with roughly monthly cut-offs (nothing is processed in July); the last 2026 cut-offs are 3 Nov and 1 Dec 2026. Salaried doctoral researcher positions are advertised and applied for separately | E2: The Doctoral Programme in Science invites applications continuously (applications will not be processed in July). | Tue 3.11.2026 | Tue 1.12.2026 || Salaried doctoral researcher positions are applied for separately from the admission process to the doctoral programme. (https://www.aalto.fi/en/doctoral-education/how-to-apply-for-doctoral-studies) | F2: https://www.aalto.fi/en/study-options/aalto-doctoral-programme-in-science-0 | H2: 2026-10-21
A3: Aalto University | B3: Application fee | C3: Not stated | D3: Not stated on the page checked | E3: (no statement found) | F3: https://www.aalto.fi/en/study-options/aalto-doctoral-programme-in-science-0 | H3: 2026-10-21
A4: Aalto University | B4: Intl fee waiver | C4: Not stated | D4: Not stated on the page checked | E4: (no statement found) | F4: https://www.aalto.fi/en/study-options/aalto-doctoral-programme-in-science-0 | H4: 2026-10-21
A5: Aalto University | B5: GRE General | C5: Not stated | D5: Not stated on the page checked | E5: (no statement found) | F5: https://www.aalto.fi/en/study-options/aalto-doctoral-programme-in-science-0 | H5: 2026-10-21
A6: Aalto University | B6: Physics GRE | C6: Not stated | D6: Not stated on the page checked | E6: (no statement found) | F6: https://www.aalto.fi/en/study-options/aalto-doctoral-programme-in-science-0 | H6: 2026-10-21
A7: Aalto University | B7: TOEFL minimum | C7: 92 | D7: TOEFL iBT 92 with 22 in Writing (2026 admissions; Home Edition accepted, MyBest not); IELTS Academic 6.5 with 6.0 in writing; results valid for two years | E7: TOEFL iBT (Internet-based Test): 92, and 22 for Writing | IELTS Academic: overall score 6.5, and writing score 6.0. | Language proficiency requirements 2026 | TOEFL test results are valid for two years from the date of the test. | F7: https://www.aalto.fi/en/doctoral-education/eligibility-and-language-requirements-in-doctoral-admissions | H7: 2026-10-21
A8: Aalto University | B8: English-test waiver (English-medium degree) | C8: Yes | D8: India is on Aalto's list: an English-medium degree (at least a 3-year bachelor's or a 1-year master's), at least half completed in English while living in India, counts if the language is stated on the certificate or transcript | E8: English proficiency can be demonstrated with an English-medium bachelor’s, master’s, licentiate or doctoral degree in one of the following countries through studies that require residence in the country in question: | Hong Kong, India, Jamaica | A minimum of one half of the degree must be completed in English in a country listed above | The degree demonstrating language skills must be at least a three-year bachelor’s degree, at least a one-year master’s degree, or a licentiate or doctoral degree. | The language of the degree must be stated unambiguously on the degree certificate or its appendix, or on the transcript of records or other official document issued by the awarding institution | F8: https://www.aalto.fi/en/doctoral-education/eligibility-and-language-requirements-in-doctoral-admissions | H8: 2026-10-21
A9: Aalto University | B9: Supervisor before admission | C9: Required | D9: You must have a supervising professor in your intended research field before you submit the application | E9: Before submitting the application, each applicant must have a supervising professor who is responsible in their intended research field to doctoral studies and the supervision of the studies. | F9: https://www.aalto.fi/en/study-options/aalto-doctoral-programme-in-science-0 | H9: 2026-10-21
A10: Aalto University | B10: PhD funding | C10: Competitive | D10: Not automatic: fund the PhD through a salaried doctoral researcher position (advertised separately) or grants. A full-time study right needs funding secured for at least 6 months; unfunded part-time study is possible in some cases. No tuition fees | E10: Those applying for a full-time right to pursue a doctoral degree must have funding secured for at least 6 months (e.g. from the employer, or through project funding or a grant). | In some cases it is also possible to start pursuing doctoral studies without funding (part-time doctoral studies). | Most Aalto doctoral students combine different funding sources during their studies. | Aalto University doctoral studies are free of tuition fees. | F10: https://www.aalto.fi/en/study-options/aalto-doctoral-programme-in-science-0 | H10: 2026-10-21
A11: Aalto University | B11: Entry route | C11: Master's usually required | D11: A relevant master's degree or equivalent; a degree from a non-Bologna country should normally include at least 4 years of study and a master's thesis | E11: To be eligible to apply in doctoral admissions, you must have a relevant Master’s degree or equivalent. | As a rule, a higher education degree (or degree combination) earned abroad in a country that does not follow the Bologna Process should include a minimum of 4 years of studies and a master’s thesis. | F11: https://www.aalto.fi/en/doctoral-education/eligibility-and-language-requirements-in-doctoral-admissions | H11: 2026-10-21
A12: Boston University | B12: Deadline (2027 entry) | C12: 2026-12-15 | D12: December 15, 23:59 ET; all documents must be posted. Year inferred. | E12: The application portal will remain open until 23:59 ET on December 15. | F12: https://www.bu.edu/physics/graduate-program/graduate-program-admissions/ | G12: year inferred | H12: 2026-10-21
A13: Boston University | B13: Application fee | C13: 95 USD | D13: USD 95 | E13: A $95 application fee. | F13: https://www.bu.edu/physics/graduate-program/graduate-program-admissions/ | H13: 2026-10-21
A14: Boston University | B14: Intl fee waiver | C14: Domestic only | D14: Central office waivers are domestic-only; international applicants may ask the program directly | E14: The central admission office of the Graduate School does not offer application fee waivers to international applicants. | F14: https://www.bu.edu/cas/admissions/phd-mfa/apply/fee-waiver/ | H14: 2026-10-21
A15: Boston University | B15: GRE General | C15: Optional | D15: Optional but strongly recommended if circumstances allow | E15: The general GRE and physics GRE are optional for all applicants to the Physics Ph.D. program. However, we strongly recommend that applicants submit their GRE and physics GRE scores with their applications, if circumstances allow. | F15: https://www.bu.edu/physics/graduate-program/graduate-program-admissions/ | H15: 2026-10-21
A16: Boston University | B16: Physics GRE | C16: Recommended | D16: Optional but strongly recommended | E16: we strongly recommend that applicants submit their GRE and physics GRE scores with their applications, if circumstances allow. | F16: https://www.bu.edu/physics/graduate-program/graduate-program-admissions/ | H16: 2026-10-21
A17: Boston University | B17: TOEFL minimum | C17: Not stated | D17: Must meet Graduate School minimum; not shown on the page checked | E17: Official English proficiency score report sent directly from testing organization which meets the minimum requirements. | F17: https://www.bu.edu/physics/graduate-program/graduate-program-admissions/ | H17: 2026-10-21
A18: Boston University | B18: English-test waiver (English-medium degree) | C18: Not stated | D18: Not stated on the page checked | E18: (no statement found) | F18: https://www.bu.edu/physics/graduate-program/graduate-program-admissions/ | H18: 2026-10-21
A19: Boston University | B19: Supervisor before admission | C19: Not stated | D19: No pre-application supervisor requirement mentioned | E19: (no statement found) | F19: https://www.bu.edu/physics/graduate-program/graduate-program-admissions/ | H19: 2026-10-21
A20: Boston University | B20: PhD funding | C20: Typical | D20: RAs and TAs receive tuition, fees and basic medical insurance plus a stipend | E20: Both research and teaching assistants receive a scholarship for tuition, fees and basic medical insurance, as well as a stipend. | F20: https://www.bu.edu/physics/graduate-program/graduate-program-admissions/ | H20: 2026-10-21
A21: Boston University | B21: Entry route | C21: Not stated | D21: Not stated on the page checked | E21: (no statement found) | F21: https://www.bu.edu/physics/graduate-program/graduate-program-admissions/ | H21: 2026-10-21
A22: California Institute of Technology | B22: Deadline (2027 entry) | C22: 2026-12-15 | D22: December 15 (catalog). Year inferred for Fall 2027. | E22: The application submission deadline for physics is December 15. | F22: https://catalog.caltech.edu/current/information-for-graduate-students/special-regulations-for-graduate-options/physics-ph/ | G22: year inferred | H22: 2026-10-21
A23: California Institute of Technology | B23: Application fee | C23: Not stated | D23: Amount not shown on the pages checked | E23: (no statement found) | F23: https://physics.caltech.edu/academics/graduate-studies/information-for-applicants | H23: 2026-10-21
A24: California Institute of Technology | B24: Intl fee waiver | C24: Limited | D24: Waivers are requested inside the online application; eligibility rules are not stated on the department page | E24: Application fee waivers are also requested and processed through the application process. | F24: https://physics.caltech.edu/academics/graduate-studies/information-for-applicants | H24: 2026-10-21
A25: California Institute of Technology | B25: GRE General | C25: Recommended | D25: Recommended, not required; considered if submitted | E25: Important graduate admissions update for applicants to the Fall 2027 cohort: The GRE general test is recommended and the GRE physics subject test is required. | F25: https://physics.caltech.edu/academics/graduate-studies/information-for-applicants | H25: 2026-10-21
A26: California Institute of Technology | B26: Physics GRE | C26: Required | D26: Physics GRE REQUIRED for the Fall 2027 cohort | E26: The GRE general test is recommended and the GRE physics subject test is required. | F26: https://physics.caltech.edu/academics/graduate-studies/information-for-applicants | H26: 2026-10-21
A27: California Institute of Technology | B27: TOEFL minimum | C27: Not stated | D27: Not shown on the department page checked | E27: (no statement found) | F27: https://physics.caltech.edu/academics/graduate-studies/information-for-applicants | H27: 2026-10-21
A28: California Institute of Technology | B28: English-test waiver (English-medium degree) | C28: Not stated | D28: Not stated on the page checked | E28: (no statement found) | F28: https://physics.caltech.edu/academics/graduate-studies/information-for-applicants | H28: 2026-10-21
A29: California Institute of Technology | B29: Supervisor before admission | C29: Not stated | D29: No pre-application supervisor requirement mentioned | E29: (no statement found) | F29: https://physics.caltech.edu/academics/graduate-studies/information-for-applicants | H29: 2026-10-21
A30: California Institute of Technology | B30: PhD funding | C30: Not stated | D30: Not stated on the page checked | E30: (no statement found) | F30: https://physics.caltech.edu/academics/graduate-studies/information-for-applicants | H30: 2026-10-21
A31: California Institute of Technology | B31: Entry route | C31: Not stated | D31: Not stated on the page checked | E31: (no statement found) | F31: https://physics.caltech.edu/academics/graduate-studies/information-for-applicants | H31: 2026-10-21
A32: Carleton University | B32: Deadline (2027 entry) | C32: 2027-01-15 | D32: January 15 (Fall entry); late applications considered if openings remain. Year inferred for Fall 2027. | E32: January 15 (late applications will be considered if openings remain) | F32: https://graduate.carleton.ca/program/physics-doctoral-programs/ | G32: year inferred | H32: 2026-10-21
A33: Carleton University | B33: Application fee | C33: 125 CAD | D33: CAD 125, non-refundable | E33: After you submit your application you will be required to pay the non-refundable application fee of C$125 | F33: https://graduate.carleton.ca/apply-online/ | H33: 2026-10-21
A34: Carleton University | B34: Intl fee waiver | C34: None | D34: Graduate application fees are not waived | E34: Application fees for graduate programs will not be waived | F34: https://graduate.carleton.ca/apply-online/ | H34: 2026-10-21
A35: Carleton University | B35: GRE General | C35: Not stated | D35: Not stated on the page checked | E35: (no statement found) | F35: https://graduate.carleton.ca/program/physics-doctoral-programs/ | H35: 2026-10-21
A36: Carleton University | B36: Physics GRE | C36: Not stated | D36: Not stated on the page checked | E36: (no statement found) | F36: https://graduate.carleton.ca/program/physics-doctoral-programs/ | H36: 2026-10-21
A37: Carleton University | B37: TOEFL minimum | C37: 86 | D37: TOEFL iBT 86 (20 reading/listening, 22 speaking/writing) for tests before Jan 21, 2026; 4.5 overall on the new scale (5.0 writing); IELTS 6.5 (6.0 per band) | E37: For exams taken before January 21, 2026: | 86 (20 in reading and listening; 22 in speaking and writing) | 4.5 overall (minimum 5.0 in writing, 4.5 in reading, listening and speaking) | F37: https://graduate.carleton.ca/international/english-second-language/ | H37: 2026-10-21
A38: Carleton University | B38: English-test waiver (English-medium degree) | C38: No | D38: Exemption only for English-taught degrees from countries whose primary language is English (India does not qualify) or a recent Canadian degree; medium-of-instruction letters are explicitly not accepted | E38: presenting official certification (transcripts) that you have completed an undergraduate or graduate degree at a university in any country in which the primary language is English | Note: Letters from your universities stating the medium of instruction is English are not acceptable. | F38: https://graduate.carleton.ca/international/english-second-language/ | H38: 2026-10-21
A39: Carleton University | B39: Supervisor before admission | C39: Not stated | D39: Not stated on the page checked | E39: (no statement found) | F39: https://graduate.carleton.ca/program/physics-doctoral-programs/ | H39: 2026-10-21
A40: Carleton University | B40: PhD funding | C40: Competitive | D40: University-level statement: applicants are automatically considered for admission funding (TA, research stipend, scholarships) and notified in the offer if eligible; no guaranteed minimum stated on the pages checked | E40: When submitting an application for admission to Carleton, students are automatically considered for funding and if eligible, will be notified in the Offer of Admission and Funding. | F40: https://graduate.carleton.ca/financial-assistance/admissions-funding/ | H40: 2026-10-21
A41: Carleton University | B41: Entry route | C41: Master's usually required | D41: An MSc is normally required; exceptional honours-BSc holders (A- average, significant research) may enter the Direct Entry PhD; MSc-to-PhD transfer possible | E41: An M.Sc. in Physics or a closely related field is normally required for admission into the Ph.D. program. | Exceptional undergraduate students holding an honours B.Sc. in Physics or a closely related field, with a minimum A- average and significant research experience, may be considered for the Direct Entry Ph.D. program. | F41: https://calendar.carleton.ca/grad/gradprograms/physics/ | H41: 2026-10-21
A42: Chalmers University of Technology | B42: Deadline (2027 entry) | C42: Per position | D42: No central deadline: doctoral positions are advertised under Vacant positions throughout the year, each with its own deadline | E42: Doctoral student positions are publicly announced and listed under Vacant positions. New positions are posted regularly throughout the year. | F42: https://www.chalmers.se/en/research/doctoral-studies/about-doctoral-studies/ | H42: 2026-10-21
A43: Chalmers University of Technology | B43: Application fee | C43: 0 (no fee) | D43: No fees: Chalmers states that doctoral programmes incur no fees | E43: Doctoral students are employed with a monthly salary, and doctoral programmes incur no fees. | F43: https://www.chalmers.se/en/research/doctoral-studies/about-doctoral-studies/ | H43: 2026-10-21
A44: Chalmers University of Technology | B44: Intl fee waiver | C44: No fee | D44: No fee to waive | E44: doctoral programmes incur no fees | F44: https://www.chalmers.se/en/research/doctoral-studies/about-doctoral-studies/ | H44: 2026-10-21
... A61: Columbia University | B61: Entry route | C61: Not stated | D61: Not stated on the pages checked | E61: (no statement found) | F61: https://www.physics.columbia.edu/content/applying-columbia-physics-graduate-program | H61: 2026-10-21
A62: Cornell University | B62: Deadline (2027 entry) | C62: 2026-12-15 | D62: December 15: all materials incl. test scores must be received. Year inferred. | E62: All required application materials and supporting documents must be submitted online and received by Cornell no later than December 15. | F62: https://physics.cornell.edu/prospective-graduate-students | G62: year inferred | H62: 2026-10-21
A63: Cornell University | B63: Application fee | C63: 105 USD | D63: USD 105 | E63: The application fee is $105. | F63: https://physics.cornell.edu/prospective-graduate-students | H63: 2026-10-21
A64: Cornell University | B64: Intl fee waiver | C64: Available | D64: Can be requested for financial hardship or extenuating circumstances (Graduate School criteria) | E64: An application fee waiver can be requested in the event of financial hardship or extenuating circumstances. | F64: https://physics.cornell.edu/prospective-graduate-students | H64: 2026-10-21
A65: Cornell University | B65: GRE General | C65: Not stated | D65: Only the Physics GRE policy is stated | E65: (no statement found) | F65: https://physics.cornell.edu/prospective-graduate-students | H65: 2026-10-21
A66: Cornell University | B66: Physics GRE | C66: Required | D66: REQUIRED for theory applicants (theoretical astro, particle, condensed matter); theory applications without it cannot be considered | E66: The physics GRE is required for applicants with interests in theoretical physics, which includes theoretical astrophysics, theoretical elementary particle physics, and theoretical condensed matter physics. Theory applications without a physics GRE score cannot be considered for admission. | F66: https://physics.cornell.edu/prospective-graduate-students | G66: theory applicants | H66: 2026-10-21
A67: Cornell University | B67: TOEFL minimum | C67: Sections | D67: No overall minimum stated; section minimums Speaking 23, Reading 20, Listening 15, Writing 20 (pre-2026) or 4.5/4/3.5/4 (new scale) | E67: The minimum TOEFL iBT score requirements for exams taken before January 2026 are: Speaking: 23, Reading: 20, Listening: 15, Writing: 20. | F67: https://physics.cornell.edu/prospective-graduate-students | H67: 2026-10-21
A68: Cornell University | B68: English-test waiver (English-medium degree) | C68: Not stated | D68: Standing exemptions on the Graduate School site (not checked) | E68: Applicants may be exempt from submitting TOEFL/IELTS scores if they meet one of the following standing exemptions outlined here. | F68: https://physics.cornell.edu/prospective-graduate-students | H68: 2026-10-21
A69: Cornell University | B69: Supervisor before admission | C69: Not stated | D69: No pre-application supervisor requirement mentioned | E69: (no statement found) | F69: https://physics.cornell.edu/prospective-graduate-students | H69: 2026-10-21
A70: Cornell University | B70: PhD funding | C70: Guaranteed | D70: 6 years of full support in good standing (fellowships, TA, RA) | E70: We provide 6 years of full financial support for all graduate students in good academic standing. | F70: https://physics.cornell.edu/prospective-graduate-students | H70: 2026-10-21
A71: Cornell University | B71: Entry route | C71: Direct from bachelor's | D71: Bachelor's (or equivalent international degree) required; terminal master's applicants fully considered | E71: A Bachelor's degree is required at the time of matriculation. | Applicants who have completed or are finishing a terminal Master's degree program will be given full consideration. | F71: https://physics.cornell.edu/prospective-graduate-students | H71: 2026-10-21
A72: Dalhousie University | B72: Deadline (2027 entry) | C72: 2027-04-01 | D72: Formal application: April 1 for non-Canadian applicants for September admission (FGS general deadline; Canadians June 1). Free department pre-application first, reviewed September 1 to April 30, so start well before. Year inferred for September 2027. | E72: For September admission: | June 1 (Canadian applicants), April 1 (non-Canadian applicants) || Pre-applications are reviewed from September 1 to April 30. | Formal application deadlines are set by the Faculty of Graduate Studies and are earlier for international applicants (https://www.dal.ca/faculty/science/physics/graduate/apply.html) | F72: https://www.dal.ca/faculty/gradstudies/apply-graduate-studies/how-to-apply.html | G72: year inferred | H72: 2026-10-21
A73: Dalhousie University | B73: Application fee | C73: 115 CAD | D73: CAD 115 for the formal FGS application (the department pre-application is free) | E73: To apply, complete the online application form and pay the $115 application fee. || There is an application fee for this step. (https://www.dal.ca/faculty/science/physics/graduate/apply.html) | F73: https://www.dal.ca/faculty/gradstudies/apply-graduate-studies/how-to-apply.html | H73: 2026-10-21
A74: Dalhousie University | B74: Intl fee waiver | C74: Not stated | D74: Not stated on the page checked | E74: (no statement found) | F74: https://www.dal.ca/faculty/gradstudies/apply-graduate-studies/how-to-apply.html | H74: 2026-10-21
A75: Dalhousie University | B75: GRE General | C75: Not required | D75: GRE not required | E75: No GRE: you don't need to take the GRE (Graduate Record Examination). | F75: https://www.dal.ca/faculty/science/physics/graduate/apply.html | H75: 2026-10-21
A76: Dalhousie University | B76: Physics GRE | C76: Not required | D76: GRE not required (no subject-test requirement listed) | E76: No GRE: you don't need to take the GRE (Graduate Record Examination). | F76: https://www.dal.ca/faculty/science/physics/graduate/apply.html | H76: 2026-10-21
A77: Dalhousie University | B77: TOEFL minimum | C77: 92 | D77: TOEFL iBT 92 (tests before Jan 21, 2026); 4.5 on the new 1-6 scale for later tests; IELTS 7 | E77: For tests taken before January 21, 2026 | Minimum acceptable score: 92 | For tests taken on or after January 21, 2026, only the 1-6 score scale* is considered: Overall score of at least 4.5. | IELTS (Academic, in-person and online) | Minimum acceptable score: 7 | F77: https://www.dal.ca/faculty/gradstudies/apply-graduate-studies/admission-requirements/english-requirements.html | H77: 2026-10-21
A78: Dalhousie University | B78: English-test waiver (English-medium degree) | C78: Conditional | D78: Waiver can be requested (not automatic) if your degree is from a recognized university with English as the language of instruction in a country where English is an official language; English is an official language of India, but confirm the waiver with the program | E78: It is possible to have this requirement waived if you completed your degree at a recognized university where the language of instruction is English and in a country where English is one of the official languages. You will be able to request this waiver during the application process. | F78: https://www.dal.ca/faculty/gradstudies/apply-graduate-studies/admission-requirements/english-requirements.html | H78: 2026-10-21
A79: Dalhousie University | B79: Supervisor before admission | C79: Required | D79: Admission depends on finding a supervisor through the free pre-application/interview; the formal application is submitted only with a supervisor's support and names the supervisor | E79: In our MSc and PhD programs, you do your research with a faculty supervisor, so admission depends on finding one. | With a supervisor's support, you then submit a formal application to Dalhousie through the Faculty of Graduate Studies. | F79: https://www.dal.ca/faculty/science/physics/graduate/apply.html | H79: 2026-10-21
A80: Dalhousie University | B80: PhD funding | C80: Guaranteed | D80: Every full-time MSc/PhD student funded; for students of primary-appointment faculty, guaranteed at least CAD 2,000/month take-home on average (CAD 24,000/yr after tuition) and CAD 33,000/yr total; PhD support normally 4 years; internationals funded on the same terms | E80: All full-time students in our MSc and PhD programs, in both Physics and Medical Physics, receive financial support. | For students supervised by faculty with a primary appointment in the Department, in either program, we guarantee: | at least $2,000 per month take-home on average ($24,000 per year), after tuition; || Funding: you're funded like everyone else. Every full-time graduate student receives financial support, whatever their citizenship (https://www.dal.ca/faculty/science/physics/graduate/international.html) | F80: https://www.dal.ca/faculty/science/physics/graduate/funding.html | H80: 2026-10-21
A81: Dalhousie University | B81: Entry route | C81: Either | D81: PhD normally after a thesis-based master's, but Physics allows direct entry from a bachelor's with supervisor agreement (typically 5 years, 7 courses); MSc-to-PhD transfer after year 1 | E81: PhD: a thesis-based master's degree. You can also go directly from a bachelor's degree to the PhD, with your supervisor's agreement. || In Physics, you can also enter the PhD directly from a bachelor's degree (https://www.dal.ca/faculty/science/physics/graduate/degrees.html) | F81: https://www.dal.ca/faculty/science/physics/graduate/apply.html | H81: 2026-10-21
A82: Delft University of Technology | B82: Deadline (2027 entry) | C82: Per position | D82: No central deadline: apply to a specific advertised PhD position (each vacancy has its own deadline) | E82: To become a PhD candidate you can apply to a specific PhD position that can be found on our vacancy website. || If you are interested in a PhD project at the faculty of Applied Sciences, we advise you to keep a close eye on the vacancy website where the latest selection of PhD vacancies can be found. (https://www.tudelft.nl/en/faculty-of-applied-sciences/research/phd) | F82: https://www.tudelft.nl/en/education/programmes/phd/phd-admission | H82: 2026-10-21
A83: Delft University of Technology | B83: Application fee | C83: Not stated | D83: Not stated on the pages checked | E83: (no statement found) | F83: https://www.tudelft.nl/en/education/programmes/phd/phd-admission | H83: 2026-10-21
A84: Delft University of Technology | B84: Intl fee waiver | C84: Not stated | D84: Not stated on the pages checked | E84: (no statement found) | F84: https://www.tudelft.nl/en/education/programmes/phd/phd-admission | H84: 2026-10-21
... A101: Durham University | B101: Entry route | C101: Either | D101: PhD entry with a First-class honours Bachelor's, or at least a 2:1 integrated Master's or a Master's degree (or equivalent) | E101: For entry to a PhD you will be required to have achieved a First Class honours Bachelor's degree, or at least a 2:1 Integrated Master's degree or a Master's degree in an appropriate subject, from a recognised university (or equivalent). | F101: https://www.durham.ac.uk/departments/academic/physics/postgraduate-study/research-degrees/how-to-apply/ | H101: 2026-10-21
A102: EPFL (École polytechnique fédérale de Lausanne) | B102: Deadline (2027 entry) | C102: 2027-04-30 | D102: Two rounds a year: October 31 and April 30. Next: Oct 31, 2026 (imminent) and Apr 30, 2027. Complete files incl. 3 letters. Years inferred. | E102: The deadlines for applications to the Physics Doctoral Program are April 30 and October 31 of each year. | F102: https://www.epfl.ch/education/phd/edpy-physics/edpy-how-to-apply/ | G102: year inferred | H102: 2026-10-21
A103: EPFL (École polytechnique fédérale de Lausanne) | B103: Application fee | C103: 0 (no fee) | D103: No application fee (enrolment fees apply later) | E103: Is there an application fee? No, there is no application fees | F103: https://www.epfl.ch/education/admission/admission-2/phd-admission-criteria-and-application/applications-faqs/ | H103: 2026-10-21
A104: EPFL (École polytechnique fédérale de Lausanne) | B104: Intl fee waiver | C104: No fee | D104: Not needed: no application fee | E104: Is there an application fee? No, there is no application fees | F104: https://www.epfl.ch/education/admission/admission-2/phd-admission-criteria-and-application/applications-faqs/ | H104: 2026-10-21
A105: EPFL (École polytechnique fédérale de Lausanne) | B105: GRE General | C105: Recommended | D105: GRE General recommended, not required | E105: The results of the GRE general test is not required but recommended. | F105: https://www.epfl.ch/education/admission/admission-2/phd-admission-criteria-and-application/applications-faqs/ | H105: 2026-10-21
A106: EPFL (École polytechnique fédérale de Lausanne) | B106: Physics GRE | C106: Not stated | D106: No Physics GRE requirement stated | E106: (no statement found) | F106: https://www.epfl.ch/education/admission/admission-2/phd-admission-criteria-and-application/applications-faqs/ | H106: 2026-10-21
A107: EPFL (École polytechnique fédérale de Lausanne) | B107: TOEFL minimum | C107: Not stated | D107: TOEFL strongly recommended (not mandatory) if your first language is not English or French; no minimum stated | E107: For foreign applicants whose first language is not English or French, we strongly recommend that they provide us with the results of the TOEFL and/or GRE test. | F107: https://www.epfl.ch/education/admission/admission-2/phd-admission-criteria-and-application/applications-faqs/ | H107: 2026-10-21
A108: EPFL (École polytechnique fédérale de Lausanne) | B108: English-test waiver (English-medium degree) | C108: Yes | D108: No English test is strictly required; proficiency in English is required and TOEFL is strongly recommended | E108: You must be proficient in English to pursue your doctoral studies at EPFL. | F108: https://www.epfl.ch/education/admission/admission-2/phd-admission-criteria-and-application/applications-faqs/ | H108: 2026-10-21
A109: EPFL (École polytechnique fédérale de Lausanne) | B109: Supervisor before admission | C109: Required | D109: Admission = eligible by committee AND a thesis advisor offers you a PhD position after interview; eligible files are shared with all thesis directors | E109: the candidate found a thesis advisor associated with the program, in a research unit that decided, after an interview, to offer him/her a PhD student position | F109: https://www.epfl.ch/education/phd/edpy-physics/edpy-how-to-apply/ | H109: 2026-10-21
A110: EPFL (École polytechnique fédérale de Lausanne) | B110: PhD funding | C110: Guaranteed | D110: Enrolment requires secured funding; lab-appointed doctoral students get an employment contract | E110: The final enrollment in the doctoral program is conditional to the choice of a thesis topic, a supervisor and a secure funding. | F110: https://www.epfl.ch/education/admission/admission-2/phd-admission-criteria-and-application/ | H110: 2026-10-21
A111: EPFL (École polytechnique fédérale de Lausanne) | B111: Entry route | C111: Master's usually required | D111: Usually after a master's; 4- or 5-year bachelor's holders may apply and should explain their education in the Statement of Objectives | E111: Doctoral studies at EPFL usually begin after a Master’s degree in the relevant discipline. Candidates with a 4-year or 5-year Bachelor’s degree may also apply | F111: https://www.epfl.ch/education/admission/admission-2/phd-admission-criteria-and-application/applications-faqs/ | H111: 2026-10-21
A112: ETH Zurich | B112: Deadline (2027 entry) | C112: Per position | D112: No central deadline: each professor recruits their own doctoral students; some posts are advertised as vacancies | E112: Each potential doctoral thesis supervisor recruits their doctoral students themselves. | F112: https://ethz.ch/en/doctorate/finding-a-place.html | H112: 2026-10-21
A113: ETH Zurich | B113: Application fee | C113: Not stated | D113: No central application process described on the page checked | E113: (no statement found) | F113: https://ethz.ch/en/doctorate/finding-a-place.html | H113: 2026-10-21
A114: ETH Zurich | B114: Intl fee waiver | C114: Not stated | D114: Not stated on the page checked | E114: (no statement found) | F114: https://ethz.ch/en/doctorate/finding-a-place.html | H114: 2026-10-21
... A121: ETH Zurich | B121: Entry route | C121: Not stated | D121: Not stated on the page checked | E121: (no statement found) | F121: https://ethz.ch/en/doctorate/finding-a-place.html | H121: 2026-10-21
A122: Georgia Institute of Technology | B122: Deadline (2027 entry) | C122: 2026-12-15 | D122: December 15. Year inferred for Fall 2027. | E122: The application deadline is December 15th. | F122: https://physics.gatech.edu/academics/graduate/admissions-info | G122: year inferred | H122: 2026-10-21
A123: Georgia Institute of Technology | B123: Application fee | C123: 105 USD | D123: USD 105 for international applicants (since Aug 1, 2023) | E123: As of August 1, 2023, the fee for international applicants is $105 per application. | F123: https://grad.gatech.edu/admissions/international/ready-to-apply | H123: 2026-10-21
A124: Georgia Institute of Technology | B124: Intl fee waiver | C124: Limited | D124: Institute waivers for outstanding undergraduate achievement or recruitment events; internationals must submit ALL materials (incl. English scores) before requesting | E124: Georgia Tech provides application fee waivers to recognize outstanding undergraduate achievement and engage prospective students in recruitment events where Georgia Tech is affiliated. | International applicants must submit all required application materials prior to requesting a fee waiver. | F124: https://grad.gatech.edu/admissions/international/ready-to-apply | H124: 2026-10-21
A125: Georgia Institute of Technology | B125: GRE General | C125: Not required | D125: General GRE not required | E125: The General GRE Test is NOT REQUIRED for all applicants. | F125: https://physics.gatech.edu/academics/graduate/admissions-info | H125: 2026-10-21
A126: Georgia Institute of Technology | B126: Physics GRE | C126: Not required | D126: Physics GRE not required | E126: The GRE Physics Test is NOT REQUIRED for all applicants. | F126: https://physics.gatech.edu/academics/graduate/admissions-info | H126: 2026-10-21
A127: Georgia Institute of Technology | B127: TOEFL minimum | C127: 106 | D127: TOEFL 106 (scores direct from ETS); IELTS 7.5 with every band 7+ (among the highest in this list) | E127: The TOEFL minimum is 106 and official scores must be sent directly from ETS. | The IELTS test minimum is 7.5, and all skills must be greater than or equal to 7. | F127: https://physics.gatech.edu/academics/graduate/admissions-info | H127: 2026-10-21
A128: Georgia Institute of Technology | B128: English-test waiver (English-medium degree) | C128: No | D128: All applicants must demonstrate English proficiency at application, regardless of citizenship | E128: All applicants must demonstrate English proficiency at the time of application, regardless of citizenship status. | F128: https://physics.gatech.edu/academics/graduate/admissions-info | H128: 2026-10-21
A129: Georgia Institute of Technology | B129: Supervisor before admission | C129: Not stated | D129: No pre-application supervisor requirement mentioned | E129: (no statement found) | F129: https://physics.gatech.edu/academics/graduate/admissions-info | H129: 2026-10-21
A130: Georgia Institute of Technology | B130: PhD funding | C130: Not stated | D130: PhD support terms not stated (MS students get no support) | E130: Our MS students are given no financial support and must pay full tuition. | F130: https://physics.gatech.edu/academics/graduate/admissions-info | H130: 2026-10-21
A131: Georgia Institute of Technology | B131: Entry route | C131: Direct from bachelor's | D131: Research-track applicants should apply straight to the PhD; a physics BS is not strictly needed if upper-level physics was taken | E131: If your career plan is to do Research, you should apply directly to the Ph.D. program – not the MS Program. | F131: https://physics.gatech.edu/academics/graduate/admissions-info | H131: 2026-10-21
A132: Harvard University | B132: Deadline (2027 entry) | C132: 2026-12-15 | D132: December 15, 2026 at 05:00 pm (PhD) | E132: Doctor of Philosophy (PhD) | Dec 15, 2026 | F132: https://gsas.harvard.edu/program/physics | H132: 2026-10-21
A133: Harvard University | B133: Application fee | C133: 105 USD | D133: USD 105, credit card only, non-refundable | E133: The application fee is $105 payable by credit card. | F133: https://gsas.harvard.edu/apply/applying-degree-programs | H133: 2026-10-21
A134: Harvard University | B134: Intl fee waiver | C134: Not stated | D134: A waiver exists; eligibility is decided by questions inside the application fee section. Whether international applicants qualify is not stated. | E134: Applicants can determine eligibility for a fee waiver by completing a series of questions in the Application Fee section of the application. | F134: https://gsas.harvard.edu/apply/applying-degree-programs | H134: 2026-10-21
... A141: Harvard University | B141: Entry route | C141: Direct from bachelor's | D141: Open to holders of a BA/BS or equivalent; for international applicants a three- or four-year undergraduate degree from an institution of recognized standing | E141: welcomes applications for admission from individuals who have or will have by the time of matriculation a BA, BS, or equivalent undergraduate degree (for prospective international students, a three- or four-year undergraduate degree from an institution of recognized standing) | F141: https://gsas.harvard.edu/apply/applying-degree-programs | H141: 2026-10-21
A142: Heidelberg University | B142: Deadline (2027 entry) | C142: 2026-11-01 | D142: Application portal deadline November 1 (for international students and anyone without prior funding). Year inferred: Nov 1, 2026. | E142: To application portal (Deadline 1 November) | F142: https://hgsfp.physik.uni-heidelberg.de/howtoapply#start | G142: year inferred; act by 2026-11-01 | H142: 2026-10-21
A143: Heidelberg University | B143: Application fee | C143: Not stated | D143: Not stated on the pages checked | E143: (no statement found) | F143: https://hgsfp.physik.uni-heidelberg.de/howtoapply#start | H143: 2026-10-21
A144: Heidelberg University | B144: Intl fee waiver | C144: Not stated | D144: Not stated on the pages checked | E144: (no statement found) | F144: https://hgsfp.physik.uni-heidelberg.de/howtoapply#start | H144: 2026-10-21
...
